{
"meta":{"test_sets":[],"test_metrics":[],"learn_metrics":[{"best_value":"Min","name":"Logloss"}],"launch_mode":"Train","parameters":"","iteration_count":1000,"learn_sets":["learn"],"name":"experiment"},
"iterations":[
{"learn":[0.5552278219],"iteration":0,"passed_time":0.07088678383,"remaining_time":70.81589705},
{"learn":[0.4513464494],"iteration":1,"passed_time":0.1415379849,"remaining_time":70.62745446},
{"learn":[0.3942657502],"iteration":2,"passed_time":0.2038906604,"remaining_time":67.75966279},
{"learn":[0.3534173827],"iteration":3,"passed_time":0.2632959275,"remaining_time":65.56068596},
{"learn":[0.3262050562],"iteration":4,"passed_time":0.3263040456,"remaining_time":64.93450508},
{"learn":[0.3070004443],"iteration":5,"passed_time":0.3934463634,"remaining_time":65.18094753},
{"learn":[0.2920777568],"iteration":6,"passed_time":0.456924574,"remaining_time":64.81801456},
{"learn":[0.2817574208],"iteration":7,"passed_time":0.5188812062,"remaining_time":64.34126957},
{"learn":[0.2744224832],"iteration":8,"passed_time":0.5883939999,"remaining_time":64.7887171},
{"learn":[0.2674914276],"iteration":9,"passed_time":0.6556363024,"remaining_time":64.90799393},
{"learn":[0.2571535733],"iteration":10,"passed_time":0.7231956051,"remaining_time":65.0218594},
{"learn":[0.2531326303],"iteration":11,"passed_time":0.8412291861,"remaining_time":69.26120299},
{"learn":[0.246133315],"iteration":12,"passed_time":0.971941725,"remaining_time":73.79280635},
{"learn":[0.2409985106],"iteration":13,"passed_time":1.050756222,"remaining_time":74.00325967},
{"learn":[0.2361986352],"iteration":14,"passed_time":1.1130941,"remaining_time":73.09317923},
{"learn":[0.2325035703],"iteration":15,"passed_time":1.175564239,"remaining_time":72.29720067},
{"learn":[0.2304405805],"iteration":16,"passed_time":1.238671542,"remaining_time":71.62436033},
{"learn":[0.2288603718],"iteration":17,"passed_time":1.302657,"remaining_time":71.06717636},
{"learn":[0.2272491173],"iteration":18,"passed_time":1.370460783,"remaining_time":70.7590541},
{"learn":[0.2255200906],"iteration":19,"passed_time":1.440231799,"remaining_time":70.57135813},
{"learn":[0.2242603607],"iteration":20,"passed_time":1.505690466,"remaining_time":70.19385554},
{"learn":[0.222190635],"iteration":21,"passed_time":1.573263755,"remaining_time":69.93872511},
{"learn":[0.2204282659],"iteration":22,"passed_time":1.641939498,"remaining_time":69.74673431},
{"learn":[0.219433375],"iteration":23,"passed_time":1.702432619,"remaining_time":69.23225982},
{"learn":[0.2180115944],"iteration":24,"passed_time":1.769122545,"remaining_time":68.99577926},
{"learn":[0.2172963186],"iteration":25,"passed_time":1.834064559,"remaining_time":68.70688001},
{"learn":[0.2166558789],"iteration":26,"passed_time":1.897012109,"remaining_time":68.36269564},
{"learn":[0.2147315136],"iteration":27,"passed_time":1.959712002,"remaining_time":68.03000234},
{"learn":[0.2139910603],"iteration":28,"passed_time":2.022839518,"remaining_time":67.7302473},
{"learn":[0.2129451732],"iteration":29,"passed_time":2.087275245,"remaining_time":67.48856624},
{"learn":[0.2125547943],"iteration":30,"passed_time":2.149207486,"remaining_time":67.18006627},
{"learn":[0.2119801532],"iteration":31,"passed_time":2.217334378,"remaining_time":67.07436494},
{"learn":[0.2115706592],"iteration":32,"passed_time":2.284757353,"remaining_time":66.95031395},
{"learn":[0.2110372749],"iteration":33,"passed_time":2.349349941,"remaining_time":66.74917772},
{"learn":[0.2103124031],"iteration":34,"passed_time":2.438717868,"remaining_time":67.2389355},
{"learn":[0.2098686073],"iteration":35,"passed_time":2.52277796,"remaining_time":67.5543876},
{"learn":[0.2095653772],"iteration":36,"passed_time":2.594701789,"remaining_time":67.53237359},
{"learn":[0.2090909192],"iteration":37,"passed_time":2.666828052,"remaining_time":67.51285754},
{"learn":[0.2083866754],"iteration":38,"passed_time":2.73573161,"remaining_time":67.41123275},
{"learn":[0.2077315138],"iteration":39,"passed_time":2.803816392,"remaining_time":67.29159342},
{"learn":[0.2073034151],"iteration":40,"passed_time":2.871173123,"remaining_time":67.15743963},
{"learn":[0.2069518805],"iteration":41,"passed_time":2.937038506,"remaining_time":66.99244973},
{"learn":[0.206763389],"iteration":42,"passed_time":3.000607438,"remaining_time":66.78096088},
{"learn":[0.2064206035],"iteration":43,"passed_time":3.065166366,"remaining_time":66.59770559},
{"learn":[0.2059129984],"iteration":44,"passed_time":3.130228434,"remaining_time":66.43040342},
{"learn":[0.2055842612],"iteration":45,"passed_time":3.197500738,"remaining_time":66.31338487},
{"learn":[0.2053366014],"iteration":46,"passed_time":3.272671649,"remaining_time":66.35864004},
{"learn":[0.20485934],"iteration":47,"passed_time":3.35653721,"remaining_time":66.57132133},
{"learn":[0.2043428059],"iteration":48,"passed_time":3.453974214,"remaining_time":67.03529547},
{"learn":[0.2042025435],"iteration":49,"passed_time":3.552526327,"remaining_time":67.49800021},
{"learn":[0.2038787219],"iteration":50,"passed_time":3.754876697,"remaining_time":69.87015658},
{"learn":[0.203679257],"iteration":51,"passed_time":3.861935224,"remaining_time":70.40604986},
{"learn":[0.2034179816],"iteration":52,"passed_time":3.943633065,"remaining_time":70.46453798},
{"learn":[0.2031689086],"iteration":53,"passed_time":4.030684115,"remaining_time":70.6116143},
{"learn":[0.2027432005],"iteration":54,"passed_time":4.100790712,"remaining_time":70.45904041},
{"learn":[0.2024727425],"iteration":55,"passed_time":4.165015992,"remaining_time":70.21026958},
{"learn":[0.2022439069],"iteration":56,"passed_time":4.230612803,"remaining_time":69.99066445},
{"learn":[0.2020572204],"iteration":57,"passed_time":4.29540923,"remaining_time":69.7633706},
{"learn":[0.201889119],"iteration":58,"passed_time":4.362171643,"remaining_time":69.57294095},
{"learn":[0.2016630607],"iteration":59,"passed_time":4.426060707,"remaining_time":69.34161774},
{"learn":[0.2015305884],"iteration":60,"passed_time":4.490757543,"remaining_time":69.12821858},
{"learn":[0.201382803],"iteration":61,"passed_time":4.555581016,"remaining_time":68.92153215},
{"learn":[0.2012837433],"iteration":62,"passed_time":4.617754612,"remaining_time":68.67993764},
{"learn":[0.2011131872],"iteration":63,"passed_time":4.675487642,"remaining_time":68.37900677},
{"learn":[0.2007465292],"iteration":64,"passed_time":4.743154078,"remaining_time":68.22844713},
{"learn":[0.2006697821],"iteration":65,"passed_time":4.816342971,"remaining_time":68.15855053},
{"learn":[0.2004942367],"iteration":66,"passed_time":4.905485065,"remaining_time":68.31070994},
{"learn":[0.2002924342],"iteration":67,"passed_time":5.02324152,"remaining_time":68.8479573},
{"learn":[0.2001025455],"iteration":68,"passed_time":5.155976869,"remaining_time":69.56832558},
{"learn":[0.1998718999],"iteration":69,"passed_time":5.298623215,"remaining_time":70.39599415},
{"learn":[0.1995893665],"iteration":70,"passed_time":5.399618374,"remaining_time":70.65134465},
{"learn":[0.1993052851],"iteration":71,"passed_time":5.502724242,"remaining_time":70.92400134},
{"learn":[0.1992714762],"iteration":72,"passed_time":5.600532847,"remaining_time":71.11909519},
{"learn":[0.1992062217],"iteration":73,"passed_time":5.697890097,"remaining_time":71.30062473},
{"learn":[0.1989852483],"iteration":74,"passed_time":5.787106036,"remaining_time":71.37430778},
{"learn":[0.1988902512],"iteration":75,"passed_time":5.868960494,"remaining_time":71.3542039},
{"learn":[0.1986491286],"iteration":76,"passed_time":5.950600465,"remaining_time":71.32992505},
{"learn":[0.1984268873],"iteration":77,"passed_time":6.03089517,"remaining_time":71.28827368},
{"learn":[0.1983050536],"iteration":78,"passed_time":6.115371736,"remaining_time":71.29439708},
{"learn":[0.1982501667],"iteration":79,"passed_time":6.189270665,"remaining_time":71.17661265},
{"learn":[0.1980932919],"iteration":80,"passed_time":6.263020466,"remaining_time":71.05821986},
{"learn":[0.1980298223],"iteration":81,"passed_time":6.339427983,"remaining_time":70.97066937},
{"learn":[0.197958227],"iteration":82,"passed_time":6.417384035,"remaining_time":70.9004959},
{"learn":[0.1979333745],"iteration":83,"passed_time":6.487541665,"remaining_time":70.74509721},
{"learn":[0.1979093436],"iteration":84,"passed_time":6.567851784,"remaining_time":70.70099273},
{"learn":[0.1978803526],"iteration":85,"passed_time":6.649228358,"remaining_time":70.66738045},
{"learn":[0.1977792215],"iteration":86,"passed_time":6.718388125,"remaining_time":70.50446389},
{"learn":[0.1977063184],"iteration":87,"passed_time":6.791604884,"remaining_time":70.38572335},
{"learn":[0.1976255177],"iteration":88,"passed_time":6.855107836,"remaining_time":70.16857572},
{"learn":[0.1975986392],"iteration":89,"passed_time":6.91964692,"remaining_time":69.96531886},
{"learn":[0.1974461621],"iteration":90,"passed_time":6.991739737,"remaining_time":69.84056506},
{"learn":[0.1973541565],"iteration":91,"passed_time":7.066231382,"remaining_time":69.74063146},
{"learn":[0.1971592679],"iteration":92,"passed_time":7.175416143,"remaining_time":69.97959614},
{"learn":[0.1971255839],"iteration":93,"passed_time":7.256621371,"remaining_time":69.94147832},
{"learn":[0.1970718523],"iteration":94,"passed_time":7.329224717,"remaining_time":69.82050915},
{"learn":[0.1970449335],"iteration":95,"passed_time":7.407098765,"remaining_time":69.75018004},
{"learn":[0.1970194021],"iteration":96,"passed_time":7.490221112,"remaining_time":69.72855324},
{"learn":[0.1969567546],"iteration":97,"passed_time":7.560887382,"remaining_time":69.59102468},
{"learn":[0.1969346765],"iteration":98,"passed_time":7.63261955,"remaining_time":69.46454762},
{"learn":[0.1968861465],"iteration":99,"passed_time":7.724509497,"remaining_time":69.52058548},
{"learn":[0.1965725491],"iteration":100,"passed_time":7.805028886,"remaining_time":69.47248484},
{"learn":[0.1964279195],"iteration":101,"passed_time":7.872419652,"remaining_time":69.30816517},
{"learn":[0.1962783481],"iteration":102,"passed_time":7.981082653,"remaining_time":69.50515669},
{"learn":[0.1962199315],"iteration":103,"passed_time":8.087710782,"remaining_time":69.67873905},
{"learn":[0.1961782964],"iteration":104,"passed_time":8.193506691,"remaining_time":69.83989036},
{"learn":[0.1959985451],"iteration":105,"passed_time":8.30424839,"remaining_time":70.03771755},
{"learn":[0.1958994756],"iteration":106,"passed_time":8.407123113,"remaining_time":70.16412094},
{"learn":[0.1958438163],"iteration":107,"passed_time":8.511294164,"remaining_time":70.29698513},
{"learn":[0.1956946492],"iteration":108,"passed_time":8.625912491,"remaining_time":70.51089936},
{"learn":[0.1955282619],"iteration":109,"passed_time":8.725471262,"remaining_time":70.59699475},
{"learn":[0.1954741207],"iteration":110,"passed_time":8.903862835,"remaining_time":71.31111766},
{"learn":[0.1954295087],"iteration":111,"passed_time":9.01592676,"remaining_time":71.48341931},
{"learn":[0.1953808033],"iteration":112,"passed_time":9.10859918,"remaining_time":71.49847321},
{"learn":[0.1953555699],"iteration":113,"passed_time":9.191233703,"remaining_time":71.43362334},
{"learn":[0.1953228103],"iteration":114,"passed_time":9.26864784,"remaining_time":71.3282899},
{"learn":[0.1952632166],"iteration":115,"passed_time":9.343256702,"remaining_time":71.2020597},
{"learn":[0.1952433314],"iteration":116,"passed_time":9.427191277,"remaining_time":71.14709314},
{"learn":[0.1949521139],"iteration":117,"passed_time":9.509312698,"remaining_time":71.07808304},
{"learn":[0.19467905],"iteration":118,"passed_time":9.600060481,"remaining_time":71.07271667},
{"learn":[0.1946444412],"iteration":119,"passed_time":9.685377619,"remaining_time":71.02610254},
{"learn":[0.1946156934],"iteration":120,"passed_time":9.794467234,"remaining_time":71.15154296},
{"learn":[0.1945794315],"iteration":121,"passed_time":9.882216519,"remaining_time":71.11955823},
{"learn":[0.1944292282],"iteration":122,"passed_time":9.973163818,"remaining_time":71.10946885},
{"learn":[0.194410851],"iteration":123,"passed_time":10.04575682,"remaining_time":70.9684111},
{"learn":[0.1943422247],"iteration":124,"passed_time":10.13962666,"remaining_time":70.9773866},
{"learn":[0.1943184119],"iteration":125,"passed_time":10.21688016,"remaining_time":70.86947034},
{"learn":[0.1942925953],"iteration":126,"passed_time":10.31469707,"remaining_time":70.90339012},
{"learn":[0.1941821296],"iteration":127,"passed_time":10.38496307,"remaining_time":70.74756093},
{"learn":[0.1941499033],"iteration":128,"passed_time":10.46866792,"remaining_time":70.68379657},
{"learn":[0.1941238554],"iteration":129,"passed_time":10.54273646,"remaining_time":70.5552363},
{"learn":[0.1940379395],"iteration":130,"passed_time":10.62628486,"remaining_time":70.49039343},
{"learn":[0.1940151885],"iteration":131,"passed_time":10.69860511,"remaining_time":70.35143358},
{"learn":[0.193935269],"iteration":132,"passed_time":10.76895876,"remaining_time":70.20065597},
{"learn":[0.1939132659],"iteration":133,"passed_time":10.84635926,"remaining_time":70.09662031},
{"learn":[0.1938860016],"iteration":134,"passed_time":10.91592356,"remaining_time":69.94276947},
{"learn":[0.1938496905],"iteration":135,"passed_time":10.99209953,"remaining_time":69.83216171},
{"learn":[0.1938315889],"iteration":136,"passed_time":11.05990907,"remaining_time":69.66935421},
{"learn":[0.1938062792],"iteration":137,"passed_time":11.1315914,"remaining_time":69.53211439},
{"learn":[0.1937851496],"iteration":138,"passed_time":11.22347287,"remaining_time":69.52093625},
{"learn":[0.1937672696],"iteration":139,"passed_time":11.28620997,"remaining_time":69.32957553},
{"learn":[0.1937402174],"iteration":140,"passed_time":11.38194147,"remaining_time":69.34104768},
{"learn":[0.1937209659],"iteration":141,"passed_time":11.46459179,"remaining_time":69.27197011},
{"learn":[0.1936968423],"iteration":142,"passed_time":11.53272448,"remaining_time":69.11569843},
{"learn":[0.1936483267],"iteration":143,"passed_time":11.61731852,"remaining_time":69.05850455},
{"learn":[0.1936298994],"iteration":144,"passed_time":11.69399667,"remaining_time":68.95425625},
{"learn":[0.1936011885],"iteration":145,"passed_time":11.77761557,"remaining_time":68.89098425},
{"learn":[0.1935802352],"iteration":146,"passed_time":11.92648362,"remaining_time":69.20605804},
{"learn":[0.1935270357],"iteration":147,"passed_time":11.99981765,"remaining_time":69.08003131},
{"learn":[0.1934978792],"iteration":148,"passed_time":12.0654146,"remaining_time":68.91052229},
{"learn":[0.1934511124],"iteration":149,"passed_time":12.12724152,"remaining_time":68.72103526},
{"learn":[0.1933220067],"iteration":150,"passed_time":12.19294396,"remaining_time":68.5550293},
{"learn":[0.193295554],"iteration":151,"passed_time":12.26198844,"remaining_time":68.40898816},
{"learn":[0.1932366113],"iteration":152,"passed_time":12.32903568,"remaining_time":68.25289689},
{"learn":[0.1932127216],"iteration":153,"passed_time":12.42843354,"remaining_time":68.27568035},
{"learn":[0.1931893011],"iteration":154,"passed_time":12.51013347,"remaining_time":68.20040504},
{"learn":[0.193168203],"iteration":155,"passed_time":12.58339539,"remaining_time":68.07939555},
{"learn":[0.1931441644],"iteration":156,"passed_time":12.65499507,"remaining_time":67.95006907},
{"learn":[0.193120608],"iteration":157,"passed_time":12.73358846,"remaining_time":67.85874357},
{"learn":[0.1930727293],"iteration":158,"passed_time":12.81672039,"remaining_time":67.79158396},
{"learn":[0.1930319911],"iteration":159,"passed_time":12.89734352,"remaining_time":67.71105346},
{"learn":[0.1928151988],"iteration":160,"passed_time":12.98112154,"remaining_time":67.64696257},
{"learn":[0.1927105134],"iteration":161,"passed_time":13.0516272,"remaining_time":67.51397279},
{"learn":[0.1926649694],"iteration":162,"passed_time":13.12818385,"remaining_time":67.41282136},
{"learn":[0.1926184897],"iteration":163,"passed_time":13.21003846,"remaining_time":67.33897656},
{"learn":[0.1925900733],"iteration":164,"passed_time":13.27511612,"remaining_time":67.18013312},
{"learn":[0.1925189874],"iteration":165,"passed_time":13.35246022,"remaining_time":67.08404713},
{"learn":[0.1924857327],"iteration":166,"passed_time":13.45545245,"remaining_time":67.11611911},
{"learn":[0.1924677163],"iteration":167,"passed_time":13.52390282,"remaining_time":66.97551873},
{"learn":[0.1923677319],"iteration":168,"passed_time":13.60083055,"remaining_time":66.87745675},
{"learn":[0.1923307484],"iteration":169,"passed_time":13.66464547,"remaining_time":66.71562201},
{"learn":[0.1923058367],"iteration":170,"passed_time":13.7307139,"remaining_time":66.56585862},
{"learn":[0.1922863425],"iteration":171,"passed_time":13.79064473,"remaining_time":66.3875223},
{"learn":[0.1922643845],"iteration":172,"passed_time":13.85442328,"remaining_time":66.22894828},
{"learn":[0.1922426571],"iteration":173,"passed_time":13.91948998,"remaining_time":66.07757888},
{"learn":[0.1922181437],"iteration":174,"passed_time":13.98464737,"remaining_time":65.92762332},
{"learn":[0.1921809292],"iteration":175,"passed_time":14.05146674,"remaining_time":65.78641245},
{"learn":[0.1921565999],"iteration":176,"passed_time":14.11931689,"remaining_time":65.65083501},
{"learn":[0.1921347878],"iteration":177,"passed_time":14.18914894,"remaining_time":65.52517094},
{"learn":[0.1921057396],"iteration":178,"passed_time":14.27214067,"remaining_time":65.46048877},
{"learn":[0.1920810226],"iteration":179,"passed_time":14.35247641,"remaining_time":65.38350365},
{"learn":[0.1920452398],"iteration":180,"passed_time":14.44431461,"remaining_time":65.35852856},
{"learn":[0.1920230393],"iteration":181,"passed_time":14.51915364,"remaining_time":65.25641581},
{"learn":[0.1919979586],"iteration":182,"passed_time":14.59736891,"remaining_time":65.16967431},
{"learn":[0.1919704271],"iteration":183,"passed_time":14.67897692,"remaining_time":65.09807156},
{"learn":[0.1919463215],"iteration":184,"passed_time":14.75932751,"remaining_time":65.0208212},
{"learn":[0.19190832],"iteration":185,"passed_time":14.83605014,"remaining_time":64.92766029},
{"learn":[0.1918586023],"iteration":186,"passed_time":14.91706817,"remaining_time":64.85334984},
{"learn":[0.1918295964],"iteration":187,"passed_time":14.99505506,"remaining_time":64.76587612},
{"learn":[0.1918096603],"iteration":188,"passed_time":15.06216898,"remaining_time":64.63184679},
{"learn":[0.1917826626],"iteration":189,"passed_time":15.13191642,"remaining_time":64.50974894},
{"learn":[0.1917575356],"iteration":190,"passed_time":15.21837122,"remaining_time":64.45896501},
{"learn":[0.1917347791],"iteration":191,"passed_time":15.2843475,"remaining_time":64.32162905},
{"learn":[0.1916991587],"iteration":192,"passed_time":15.36117917,"remaining_time":64.23042273},
{"learn":[0.1916528608],"iteration":193,"passed_time":15.44108447,"remaining_time":64.15213443},
{"learn":[0.1916039122],"iteration":194,"passed_time":15.51020154,"remaining_time":64.02929353},
{"learn":[0.1915706757],"iteration":195,"passed_time":15.58193416,"remaining_time":63.91772991},
{"learn":[0.191546086],"iteration":196,"passed_time":15.6487662,"remaining_time":63.78659522},
{"learn":[0.1914481886],"iteration":197,"passed_time":15.73256606,"remaining_time":63.72483827},
{"learn":[0.1913612067],"iteration":198,"passed_time":15.81563715,"remaining_time":63.65992643},
{"learn":[0.1911832027],"iteration":199,"passed_time":15.8806485,"remaining_time":63.52259402},
{"learn":[0.1911528322],"iteration":200,"passed_time":15.941789,"remaining_time":63.37059407},
{"learn":[0.191077856],"iteration":201,"passed_time":16.00806117,"remaining_time":63.23976641},
{"learn":[0.1910326382],"iteration":202,"passed_time":16.07161601,"remaining_time":63.0989062},
{"learn":[0.1910097009],"iteration":203,"passed_time":16.13471379,"remaining_time":62.95702048},
{"learn":[0.1909793782],"iteration":204,"passed_time":16.19620412,"remaining_time":62.80966966},
{"learn":[0.19086474],"iteration":205,"passed_time":16.26337519,"remaining_time":62.68504806},
{"learn":[0.1908337728],"iteration":206,"passed_time":16.33313187,"remaining_time":62.57088684},
{"learn":[0.190812077],"iteration":207,"passed_time":16.39504932,"remaining_time":62.42730317},
{"learn":[0.1907816391],"iteration":208,"passed_time":16.45854038,"remaining_time":62.29045664},
{"learn":[0.1907438972],"iteration":209,"passed_time":16.52617359,"remaining_time":62.16989112},
{"learn":[0.1907209485],"iteration":210,"passed_time":16.59311583,"remaining_time":62.04724355},
{"learn":[0.1906921883],"iteration":211,"passed_time":16.66474147,"remaining_time":61.9425296},
{"learn":[0.1906740977],"iteration":212,"passed_time":16.72317515,"remaining_time":61.78938424},
{"learn":[0.1906513536],"iteration":213,"passed_time":16.80877654,"remaining_time":61.73690821},
{"learn":[0.1906238619],"iteration":214,"passed_time":16.87294944,"remaining_time":61.60588518},
{"learn":[0.1905989024],"iteration":215,"passed_time":16.95580271,"remaining_time":61.54328391},
{"learn":[0.1905796579],"iteration":216,"passed_time":17.0235303,"remaining_time":61.42591807},
{"learn":[0.1905150252],"iteration":217,"passed_time":17.08750011,"remaining_time":61.29552792},
{"learn":[0.1904918261],"iteration":218,"passed_time":17.1632042,"remaining_time":61.20759125},
{"learn":[0.1904426846],"iteration":219,"passed_time":17.23257453,"remaining_time":61.09730968},
{"learn":[0.1904113722],"iteration":220,"passed_time":17.30070299,"remaining_time":60.98302094},
{"learn":[0.190390796],"iteration":221,"passed_time":17.39042939,"remaining_time":60.94483814},
{"learn":[0.190364997],"iteration":222,"passed_time":17.45918558,"remaining_time":60.83312645},
{"learn":[0.1903474245],"iteration":223,"passed_time":17.53974298,"remaining_time":60.76268105},
{"learn":[0.1902506374],"iteration":224,"passed_time":17.60686004,"remaining_time":60.64585125},
{"learn":[0.1902026921],"iteration":225,"passed_time":17.67944483,"remaining_time":60.54818717},
{"learn":[0.190111491],"iteration":226,"passed_time":17.74508738,"remaining_time":60.42710372},
{"learn":[0.190085277],"iteration":227,"passed_time":17.81959143,"remaining_time":60.33651133},
{"learn":[0.1900654069],"iteration":228,"passed_time":17.89015587,"remaining_time":60.23279552},
{"learn":[0.1900438622],"iteration":229,"passed_time":17.98874369,"remaining_time":60.22318541},
{"learn":[0.189998987],"iteration":230,"passed_time":18.0652131,"remaining_time":60.13917263},
{"learn":[0.1899637319],"iteration":231,"passed_time":18.14451079,"remaining_time":60.06458745},
{"learn":[0.1899401226],"iteration":232,"passed_time":18.23135766,"remaining_time":60.01481256},
{"learn":[0.1899151161],"iteration":233,"passed_time":18.31024726,"remaining_time":59.93867265},
{"learn":[0.1898515691],"iteration":234,"passed_time":18.38786114,"remaining_time":59.85835649},
{"learn":[0.189827006],"iteration":235,"passed_time":18.47964208,"remaining_time":59.82392605},
{"learn":[0.1898119426],"iteration":236,"passed_time":18.55999547,"remaining_time":59.7522217},
{"learn":[0.1897842877],"iteration":237,"passed_time":18.63291294,"remaining_time":59.65663724},
{"learn":[0.1897307778],"iteration":238,"passed_time":18.70378127,"remaining_time":59.55471778},
{"learn":[0.1897089956],"iteration":239,"passed_time":18.77527755,"remaining_time":59.45504559},
{"learn":[0.1896816547],"iteration":240,"passed_time":18.84280379,"remaining_time":59.34310405},
{"learn":[0.1896627325],"iteration":241,"passed_time":18.90876939,"remaining_time":59.22664131},
{"learn":[0.1896053802],"iteration":242,"passed_time":18.97541215,"remaining_time":59.11270368},
{"learn":[0.1895817572],"iteration":243,"passed_time":19.04427476,"remaining_time":59.00603163},
{"learn":[0.1895598297],"iteration":244,"passed_time":19.10761618,"remaining_time":58.88265394},
{"learn":[0.1895461008],"iteration":245,"passed_time":19.16832274,"remaining_time":58.7516884},
{"learn":[0.1895241869],"iteration":246,"passed_time":19.23210461,"remaining_time":58.63066709},
{"learn":[0.1894918717],"iteration":247,"passed_time":19.29964853,"remaining_time":58.52151489},
{"learn":[0.1894675875],"iteration":248,"passed_time":19.37168649,"remaining_time":58.42625121},
{"learn":[0.18944934],"iteration":249,"passed_time":19.43774984,"remaining_time":58.31324952},
{"learn":[0.1894288254],"iteration":250,"passed_time":19.50745815,"remaining_time":58.21149864},
{"learn":[0.1894063168],"iteration":251,"passed_time":19.57457295,"remaining_time":58.10230385},
{"learn":[0.1893874862],"iteration":252,"passed_time":19.63899933,"remaining_time":57.98550394},
{"learn":[0.189329168],"iteration":253,"passed_time":19.70646631,"remaining_time":57.87804673},
{"learn":[0.1893126384],"iteration":254,"passed_time":19.77837913,"remaining_time":57.78389197},
{"learn":[0.1892813791],"iteration":255,"passed_time":19.84146303,"remaining_time":57.66425194},
{"learn":[0.1892663544],"iteration":256,"passed_time":19.90911496,"remaining_time":57.55825843},
{"learn":[0.1892417459],"iteration":257,"passed_time":19.97302153,"remaining_time":57.4417906},
{"learn":[0.1892305483],"iteration":258,"passed_time":20.04174017,"remaining_time":57.33949601},
{"learn":[0.1892015794],"iteration":259,"passed_time":20.10517855,"remaining_time":57.22243126},
{"learn":[0.1891529292],"iteration":260,"passed_time":20.16867516,"remaining_time":57.10594232},
{"learn":[0.1891366701],"iteration":261,"passed_time":20.23254551,"remaining_time":56.99091063},
{"learn":[0.1891226619],"iteration":262,"passed_time":20.37436236,"remaining_time":57.09469605},
{"learn":[0.1891052007],"iteration":263,"passed_time":20.44015066,"remaining_time":56.98466244},
{"learn":[0.1890843703],"iteration":264,"passed_time":20.50680194,"remaining_time":56.87735633},
{"learn":[0.1890502647],"iteration":265,"passed_time":20.57325733,"remaining_time":56.76981534},
{"learn":[0.1890179291],"iteration":266,"passed_time":20.64215093,"remaining_time":56.66927576},
{"learn":[0.1889917533],"iteration":267,"passed_time":20.71405501,"remaining_time":56.57719503},
{"learn":[0.1889705216],"iteration":268,"passed_time":20.77742317,"remaining_time":56.46206818},
{"learn":[0.1888950441],"iteration":269,"passed_time":20.8382335,"remaining_time":56.34040909},
{"learn":[0.1888716163],"iteration":270,"passed_time":20.90347948,"remaining_time":56.23113115},
{"learn":[0.188853342],"iteration":271,"passed_time":20.97817273,"remaining_time":56.14746231},
{"learn":[0.1888321519],"iteration":272,"passed_time":21.04590584,"remaining_time":56.04532433},
{"learn":[0.1888063552],"iteration":273,"passed_time":21.11237451,"remaining_time":55.9400872},
{"learn":[0.1887893813],"iteration":274,"passed_time":21.1743094,"remaining_time":55.82317933},
{"learn":[0.1887702909],"iteration":275,"passed_time":21.24766101,"remaining_time":55.73661801},
{"learn":[0.1887437403],"iteration":276,"passed_time":21.31109934,"remaining_time":55.62427734},
{"learn":[0.1887244876],"iteration":277,"passed_time":21.37671761,"remaining_time":55.51795006},
{"learn":[0.1887000849],"iteration":278,"passed_time":21.43979641,"remaining_time":55.405352},
{"learn":[0.1886731721],"iteration":279,"passed_time":21.50248534,"remaining_time":55.29210516},
{"learn":[0.1886551556],"iteration":280,"passed_time":21.56265036,"remaining_time":55.17276017},
{"learn":[0.1886226417],"iteration":281,"passed_time":21.62335053,"remaining_time":55.05519744},
{"learn":[0.1886016637],"iteration":282,"passed_time":21.68789742,"remaining_time":54.9477825},
{"learn":[0.1885797726],"iteration":283,"passed_time":21.7564658,"remaining_time":54.85080814},
{"learn":[0.1885572037],"iteration":284,"passed_time":21.82013201,"remaining_time":54.7417347},
{"learn":[0.1885366329],"iteration":285,"passed_time":21.88726712,"remaining_time":54.6416389},
{"learn":[0.1885107339],"iteration":286,"passed_time":21.95047232,"remaining_time":54.53200962},
{"learn":[0.1883951251],"iteration":287,"passed_time":22.01791573,"remaining_time":54.43318056},
{"learn":[0.1882745665],"iteration":288,"passed_time":22.09141295,"remaining_time":54.34946232},
{"learn":[0.1882471942],"iteration":289,"passed_time":22.15299827,"remaining_time":54.23665094},
{"learn":[0.1881431249],"iteration":290,"passed_time":22.23250696,"remaining_time":54.16786059},
{"learn":[0.1881080717],"iteration":291,"passed_time":22.30206213,"remaining_time":54.07486297},
{"learn":[0.1880770305],"iteration":292,"passed_time":22.38056387,"remaining_time":54.00361317},
{"learn":[0.1880605706],"iteration":293,"passed_time":22.45119552,"remaining_time":53.9134151},
{"learn":[0.1880382641],"iteration":294,"passed_time":22.51708829,"remaining_time":53.81202456},
{"learn":[0.1880021511],"iteration":295,"passed_time":22.58462252,"remaining_time":53.71477789},
{"learn":[0.1879838306],"iteration":296,"passed_time":22.64582764,"remaining_time":53.60275027},
{"learn":[0.1879555226],"iteration":297,"passed_time":22.71493589,"remaining_time":53.50968119},
{"learn":[0.1879415786],"iteration":298,"passed_time":22.7902029,"remaining_time":53.43121149},
{"learn":[0.187897292],"iteration":299,"passed_time":22.85695207,"remaining_time":53.33288815},
{"learn":[0.1878786416],"iteration":300,"passed_time":22.92524802,"remaining_time":53.23836666},
{"learn":[0.1878479229],"iteration":301,"passed_time":22.99512821,"remaining_time":53.14768044},
{"learn":[0.1877823684],"iteration":302,"passed_time":23.07694987,"remaining_time":53.08460085},
{"learn":[0.1877649027],"iteration":303,"passed_time":23.14670073,"remaining_time":52.9937622},
{"learn":[0.1877297197],"iteration":304,"passed_time":23.22245402,"remaining_time":52.91673949},
{"learn":[0.1877024159],"iteration":305,"passed_time":23.29541226,"remaining_time":52.83338597},
{"learn":[0.1876813546],"iteration":306,"passed_time":23.36528696,"remaining_time":52.74313963},
{"learn":[0.1876593275],"iteration":307,"passed_time":23.44218995,"remaining_time":52.66881639},
{"learn":[0.1876328581],"iteration":308,"passed_time":23.51343082,"remaining_time":52.58181455},
{"learn":[0.1876104645],"iteration":309,"passed_time":23.58783825,"remaining_time":52.50196255},
{"learn":[0.1875885604],"iteration":310,"passed_time":23.65167601,"remaining_time":52.39872916},
{"learn":[0.1875612381],"iteration":311,"passed_time":23.73679947,"remaining_time":52.342686},
{"learn":[0.187546388],"iteration":312,"passed_time":23.80435548,"remaining_time":52.24789846},
{"learn":[0.1874647708],"iteration":313,"passed_time":23.87402041,"remaining_time":52.15789172},
{"learn":[0.1874435058],"iteration":314,"passed_time":23.94449928,"remaining_time":52.06978415},
{"learn":[0.1874243818],"iteration":315,"passed_time":24.00411333,"remaining_time":51.95827063},
{"learn":[0.1874042493],"iteration":316,"passed_time":24.06405708,"remaining_time":51.84779491},
{"learn":[0.187376861],"iteration":317,"passed_time":24.12434103,"remaining_time":51.73836661},
{"learn":[0.1873551981],"iteration":318,"passed_time":24.20472945,"remaining_time":51.67216538},
{"learn":[0.1873358519],"iteration":319,"passed_time":24.27194567,"remaining_time":51.57788454},
{"learn":[0.1873136034],"iteration":320,"passed_time":24.33838624,"remaining_time":51.48213165},
{"learn":[0.1872445023],"iteration":321,"passed_time":24.4096623,"remaining_time":51.39674237},
{"learn":[0.1872164589],"iteration":322,"passed_time":24.4815191,"remaining_time":51.31265768},
{"learn":[0.1872009971],"iteration":323,"passed_time":24.55725248,"remaining_time":51.23673666},
{"learn":[0.1871770593],"iteration":324,"passed_time":24.63975981,"remaining_time":51.17488575},
{"learn":[0.1871590431],"iteration":325,"passed_time":24.72018263,"remaining_time":51.10859845},
{"learn":[0.1870934281],"iteration":326,"passed_time":24.80143705,"remaining_time":51.0439362},
{"learn":[0.1870785734],"iteration":327,"passed_time":24.88847468,"remaining_time":50.99102129},
{"learn":[0.1870559566],"iteration":328,"passed_time":24.96277029,"remaining_time":50.91191144},
{"learn":[0.1870332325],"iteration":329,"passed_time":25.0458314,"remaining_time":50.85062738},
{"learn":[0.1870177132],"iteration":330,"passed_time":25.11773805,"remaining_time":50.76666694},
{"learn":[0.1870043053],"iteration":331,"passed_time":25.19409648,"remaining_time":50.6917363},
{"learn":[0.1869688629],"iteration":332,"passed_time":25.27653465,"remaining_time":50.62897482},
{"learn":[0.1869515667],"iteration":333,"passed_time":25.34036272,"remaining_time":50.52898673},
{"learn":[0.1868890147],"iteration":334,"passed_time":25.4019214,"remaining_time":50.42470964},
{"learn":[0.1868670109],"iteration":335,"passed_time":25.46617143,"remaining_time":50.32600545},
{"learn":[0.1868441971],"iteration":336,"passed_time":25.52856201,"remaining_time":50.22384751},
{"learn":[0.1868298977],"iteration":337,"passed_time":25.58889412,"remaining_time":50.11789323},
{"learn":[0.1868058098],"iteration":338,"passed_time":25.65792282,"remaining_time":50.02916515},
{"learn":[0.1867924],"iteration":339,"passed_time":25.72414408,"remaining_time":49.93510321},
{"learn":[0.1867665324],"iteration":340,"passed_time":25.78653364,"remaining_time":49.83379962},
{"learn":[0.186751799],"iteration":341,"passed_time":25.84966407,"remaining_time":49.734149},
{"learn":[0.1866953265],"iteration":342,"passed_time":25.91491119,"remaining_time":49.63876575},
{"learn":[0.1866789103],"iteration":343,"passed_time":25.98204874,"remaining_time":49.54716271},
{"learn":[0.1866610197],"iteration":344,"passed_time":26.04733103,"remaining_time":49.4521792},
{"learn":[0.186646894],"iteration":345,"passed_time":26.11574509,"remaining_time":49.36328696},
{"learn":[0.1866339151],"iteration":346,"passed_time":26.18371679,"remaining_time":49.2736803},
{"learn":[0.1865480902],"iteration":347,"passed_time":26.25490459,"remaining_time":49.19022355},
{"learn":[0.1865328809],"iteration":348,"passed_time":26.33276118,"remaining_time":49.11927659},
{"learn":[0.1865143331],"iteration":349,"passed_time":26.39821726,"remaining_time":49.02526063},
{"learn":[0.1864991991],"iteration":350,"passed_time":26.46738463,"remaining_time":48.93826959},
{"learn":[0.1864783882],"iteration":351,"passed_time":26.533996,"remaining_time":48.84667446},
{"learn":[0.186452443],"iteration":352,"passed_time":26.61131073,"remaining_time":48.77483865},
{"learn":[0.1864386193],"iteration":353,"passed_time":26.67866694,"remaining_time":48.68479898},
{"learn":[0.1864144567],"iteration":354,"passed_time":26.74479314,"remaining_time":48.59265233},
{"learn":[0.1863946025],"iteration":355,"passed_time":26.82920796,"remaining_time":48.53373574},
{"learn":[0.1863364921],"iteration":356,"passed_time":26.88821925,"remaining_time":48.42892151},
{"learn":[0.1863155012],"iteration":357,"passed_time":26.95486332,"remaining_time":48.33805098},
{"learn":[0.1862993221],"iteration":358,"passed_time":27.01487351,"remaining_time":48.23547052},
{"learn":[0.1862816689],"iteration":359,"passed_time":27.08411937,"remaining_time":48.14954554},
{"learn":[0.1862519875],"iteration":360,"passed_time":27.15298801,"remaining_time":48.06304525},
{"learn":[0.186191755],"iteration":361,"passed_time":27.21955929,"remaining_time":47.97259345},
{"learn":[0.1861717608],"iteration":362,"passed_time":27.29217397,"remaining_time":47.89287828},
{"learn":[0.1860901773],"iteration":363,"passed_time":27.35631224,"remaining_time":47.79839171},
{"learn":[0.1860788285],"iteration":364,"passed_time":27.42252485,"remaining_time":47.70768021},
{"learn":[0.186055172],"iteration":365,"passed_time":27.4935318,"remaining_time":47.62540755},
{"learn":[0.1860310748],"iteration":366,"passed_time":27.56032106,"remaining_time":47.5359216},
{"learn":[0.1860128228],"iteration":367,"passed_time":27.64247063,"remaining_time":47.4729387},
{"learn":[0.1859922596],"iteration":368,"passed_time":27.70796567,"remaining_time":47.38137219},
{"learn":[0.1859703384],"iteration":369,"passed_time":27.77548398,"remaining_time":47.29339164},
{"learn":[0.1859524481],"iteration":370,"passed_time":27.83863749,"remaining_time":47.19812124},
{"learn":[0.1859233609],"iteration":371,"passed_time":27.89768832,"remaining_time":47.09609749},
{"learn":[0.1859006624],"iteration":372,"passed_time":27.96398687,"remaining_time":47.00648731},
{"learn":[0.1858810205],"iteration":373,"passed_time":28.02565426,"remaining_time":46.90925017},
{"learn":[0.1858569466],"iteration":374,"passed_time":28.08409366,"remaining_time":46.80682277},
{"learn":[0.1858458537],"iteration":375,"passed_time":28.14132823,"remaining_time":46.70262982},
{"learn":[0.1858266202],"iteration":376,"passed_time":28.20443592,"remaining_time":46.60839146},
{"learn":[0.1858069349],"iteration":377,"passed_time":28.26419897,"remaining_time":46.50881418},
{"learn":[0.1857901447],"iteration":378,"passed_time":28.32147055,"remaining_time":46.40536467},
{"learn":[0.1857712038],"iteration":379,"passed_time":28.39653636,"remaining_time":46.3311909},
{"learn":[0.1857516136],"iteration":380,"passed_time":28.48372065,"remaining_time":46.276701},
{"learn":[0.1857304436],"iteration":381,"passed_time":28.56202095,"remaining_time":46.20766741},
{"learn":[0.1857066626],"iteration":382,"passed_time":28.64768675,"remaining_time":46.15045098},
{"learn":[0.1855713771],"iteration":383,"passed_time":28.7313305,"remaining_time":46.08984267},
{"learn":[0.185535005],"iteration":384,"passed_time":28.81277435,"remaining_time":46.02560059},
{"learn":[0.1855132652],"iteration":385,"passed_time":28.95361279,"remaining_time":46.05574676},
{"learn":[0.1854947664],"iteration":386,"passed_time":29.13559943,"remaining_time":46.15018721},
{"learn":[0.1854737883],"iteration":387,"passed_time":29.22002028,"remaining_time":46.08931033},
{"learn":[0.1854518853],"iteration":388,"passed_time":29.28888538,"remaining_time":46.00387909},
{"learn":[0.185426223],"iteration":389,"passed_time":29.38287401,"remaining_time":45.95782859},
{"learn":[0.1854122761],"iteration":390,"passed_time":29.46170465,"remaining_time":45.88792361},
{"learn":[0.1853927562],"iteration":391,"passed_time":29.53268977,"remaining_time":45.80580455},
{"learn":[0.1853757899],"iteration":392,"passed_time":29.59703172,"remaining_time":45.71348157},
{"learn":[0.185359821],"iteration":393,"passed_time":29.66313969,"remaining_time":45.62401689},
{"learn":[0.1853350401],"iteration":394,"passed_time":29.72970229,"remaining_time":45.5353668},
{"learn":[0.1853231332],"iteration":395,"passed_time":29.80834506,"remaining_time":45.46525358},
{"learn":[0.1853050063],"iteration":396,"passed_time":29.88184874,"remaining_time":45.38729167},
{"learn":[0.1852812277],"iteration":397,"passed_time":29.96470422,"remaining_time":45.32349734},
{"learn":[0.1852674269],"iteration":398,"passed_time":30.03329113,"remaining_time":45.23811522},
{"learn":[0.1852545185],"iteration":399,"passed_time":30.09530677,"remaining_time":45.14296015},
{"learn":[0.1852318121],"iteration":400,"passed_time":30.16364565,"remaining_time":45.05741582},
{"learn":[0.1852162171],"iteration":401,"passed_time":30.23086115,"remaining_time":44.970286},
{"learn":[0.1851973846],"iteration":402,"passed_time":30.30028333,"remaining_time":44.88652394},
{"learn":[0.1851839856],"iteration":403,"passed_time":30.37364563,"remaining_time":44.80864554},
{"learn":[0.1851574232],"iteration":404,"passed_time":30.44539782,"remaining_time":44.72842396},
{"learn":[0.1851322055],"iteration":405,"passed_time":30.51394933,"remaining_time":44.64356133},
{"learn":[0.1851203255],"iteration":406,"passed_time":30.58020882,"remaining_time":44.55543939},
{"learn":[0.1850982309],"iteration":407,"passed_time":30.65225633,"remaining_time":44.4758229},
{"learn":[0.1850747493],"iteration":408,"passed_time":30.71904428,"remaining_time":44.38864345},
{"learn":[0.185053119],"iteration":409,"passed_time":30.78493501,"remaining_time":44.30027233},
{"learn":[0.1850303738],"iteration":410,"passed_time":30.85644577,"remaining_time":44.22006462},
{"learn":[0.1850055046],"iteration":411,"passed_time":30.92787347,"remaining_time":44.13978058},
{"learn":[0.1849954534],"iteration":412,"passed_time":30.99377331,"remaining_time":44.05168264},
{"learn":[0.1849671907],"iteration":413,"passed_time":31.06094496,"remaining_time":43.96549214},
{"learn":[0.1849503787],"iteration":414,"passed_time":31.14301251,"remaining_time":43.90039113},
{"learn":[0.1849359511],"iteration":415,"passed_time":31.21219655,"remaining_time":43.81712207},
{"learn":[0.1849148764],"iteration":416,"passed_time":31.28281088,"remaining_time":43.73592024},
{"learn":[0.1848972611],"iteration":417,"passed_time":31.35530387,"remaining_time":43.65738482},
{"learn":[0.1848802831],"iteration":418,"passed_time":31.42363104,"remaining_time":43.57310176},
{"learn":[0.1848240468],"iteration":419,"passed_time":31.51020657,"remaining_time":43.51409478},
{"learn":[0.1848137355],"iteration":420,"passed_time":31.59046942,"remaining_time":43.44627505},
{"learn":[0.184789454],"iteration":421,"passed_time":31.66038222,"remaining_time":43.3642202},
{"learn":[0.1847710335],"iteration":422,"passed_time":31.72703059,"remaining_time":43.27776986},
{"learn":[0.184755697],"iteration":423,"passed_time":31.79802918,"remaining_time":43.19732266},
{"learn":[0.1847324789],"iteration":424,"passed_time":31.8581993,"remaining_time":43.10226964},
{"learn":[0.1847113071],"iteration":425,"passed_time":31.92130822,"remaining_time":43.01134018},
{"learn":[0.1846934164],"iteration":426,"passed_time":31.98846689,"remaining_time":42.92597547},
{"learn":[0.184674436],"iteration":427,"passed_time":32.06765818,"remaining_time":42.85677683},
{"learn":[0.1846603976],"iteration":428,"passed_time":32.15201823,"remaining_time":42.79441121},
{"learn":[0.1846171578],"iteration":429,"passed_time":32.23408165,"remaining_time":42.72889893},
{"learn":[0.1846018761],"iteration":430,"passed_time":32.31666111,"remaining_time":42.66399112},
{"learn":[0.1845760856],"iteration":431,"passed_time":32.41058535,"remaining_time":42.61391778},
{"learn":[0.1845578947],"iteration":432,"passed_time":32.4894007,"remaining_time":42.54385727},
{"learn":[0.1845410277],"iteration":433,"passed_time":32.57048029,"remaining_time":42.47670932},
{"learn":[0.1845246953],"iteration":434,"passed_time":32.66155438,"remaining_time":42.42247868},
{"learn":[0.1844988759],"iteration":435,"passed_time":32.76724702,"remaining_time":42.38698927},
{"learn":[0.184449917],"iteration":436,"passed_time":32.84315647,"remaining_time":42.31280799},
{"learn":[0.1844305375],"iteration":437,"passed_time":32.93278132,"remaining_time":42.25621713},
{"learn":[0.1844080817],"iteration":438,"passed_time":33.03200692,"remaining_time":42.21174461},
{"learn":[0.1843942236],"iteration":439,"passed_time":33.10862793,"remaining_time":42.13825373},
{"learn":[0.1843761728],"iteration":440,"passed_time":33.18645891,"remaining_time":42.06628239},
{"learn":[0.1843604381],"iteration":441,"passed_time":33.2699455,"remaining_time":42.00142441},
{"learn":[0.1843418147],"iteration":442,"passed_time":33.36010027,"remaining_time":41.94486648},
{"learn":[0.1843262956],"iteration":443,"passed_time":33.44412108,"remaining_time":41.88047595},
{"learn":[0.1843093711],"iteration":444,"passed_time":33.54139283,"remaining_time":41.83252364},
{"learn":[0.1842852279],"iteration":445,"passed_time":33.65052417,"remaining_time":41.7990816},
{"learn":[0.1842605318],"iteration":446,"passed_time":33.73619641,"remaining_time":41.73627878},
{"learn":[0.1842401829],"iteration":447,"passed_time":33.81514379,"remaining_time":41.66508788},
{"learn":[0.1842205796],"iteration":448,"passed_time":33.90997445,"remaining_time":41.61335395},
{"learn":[0.1842053707],"iteration":449,"passed_time":33.99078435,"remaining_time":41.54429198},
{"learn":[0.1841465435],"iteration":450,"passed_time":34.05971803,"remaining_time":41.46072106},
{"learn":[0.184132295],"iteration":451,"passed_time":34.12771888,"remaining_time":41.37608395},
{"learn":[0.1841006469],"iteration":452,"passed_time":34.19549526,"remaining_time":41.29124925},
{"learn":[0.1840695239],"iteration":453,"passed_time":34.26550522,"remaining_time":41.20917588},
{"learn":[0.1840437272],"iteration":454,"passed_time":34.33845919,"remaining_time":41.13068189},
{"learn":[0.1840310222],"iteration":455,"passed_time":34.41340095,"remaining_time":41.05458359},
{"learn":[0.1840097371],"iteration":456,"passed_time":34.49661419,"remaining_time":40.98831839},
{"learn":[0.1839915909],"iteration":457,"passed_time":34.58290129,"remaining_time":40.92561681},
{"learn":[0.1839765462],"iteration":458,"passed_time":34.66000849,"remaining_time":40.85199258},
{"learn":[0.1839604357],"iteration":459,"passed_time":34.72927932,"remaining_time":40.76915398},
{"learn":[0.1839449184],"iteration":460,"passed_time":34.79415064,"remaining_time":40.68123035},
{"learn":[0.1839282257],"iteration":461,"passed_time":34.86246481,"remaining_time":40.59741573},
{"learn":[0.1839116377],"iteration":462,"passed_time":34.93315353,"remaining_time":40.51642213},
{"learn":[0.183893924],"iteration":463,"passed_time":35.0222604,"remaining_time":40.45674908},
{"learn":[0.1838757561],"iteration":464,"passed_time":35.11326756,"remaining_time":40.3991358},
{"learn":[0.1838570807],"iteration":465,"passed_time":35.2120252,"remaining_time":40.35026064},
{"learn":[0.1838416366],"iteration":466,"passed_time":35.29588358,"remaining_time":40.28416691},
{"learn":[0.1838177539],"iteration":467,"passed_time":35.37821018,"remaining_time":40.21625602},
{"learn":[0.1837939356],"iteration":468,"passed_time":35.44306845,"remaining_time":40.12850607},
{"learn":[0.1837706377],"iteration":469,"passed_time":35.51014001,"remaining_time":40.04334938},
{"learn":[0.1837489787],"iteration":470,"passed_time":35.59186825,"remaining_time":39.97473101},
{"learn":[0.1837313312],"iteration":471,"passed_time":35.66715467,"remaining_time":39.89885099},
{"learn":[0.183712143],"iteration":472,"passed_time":35.74413981,"remaining_time":39.82486613},
{"learn":[0.1836983813],"iteration":473,"passed_time":35.81502129,"remaining_time":39.74409536},
{"learn":[0.1836784821],"iteration":474,"passed_time":35.88940545,"remaining_time":39.66723761},
{"learn":[0.1836534389],"iteration":475,"passed_time":35.95644545,"remaining_time":39.58230549},
{"learn":[0.1836353132],"iteration":476,"passed_time":36.02458532,"remaining_time":39.49865434},
{"learn":[0.1836227511],"iteration":477,"passed_time":36.08931841,"remaining_time":39.41134772},
{"learn":[0.1836031382],"iteration":478,"passed_time":36.16780424,"remaining_time":39.33909397},
{"learn":[0.183568528],"iteration":479,"passed_time":36.23725473,"remaining_time":39.25702595},
{"learn":[0.1835554951],"iteration":480,"passed_time":36.30595495,"remaining_time":39.17420088},
{"learn":[0.1835393942],"iteration":481,"passed_time":36.37189579,"remaining_time":39.08846892},
{"learn":[0.183513225],"iteration":482,"passed_time":36.43394692,"remaining_time":38.9986554},
{"learn":[0.1834907362],"iteration":483,"passed_time":36.50444346,"remaining_time":38.91796038},
{"learn":[0.1834716145],"iteration":484,"passed_time":36.57247421,"remaining_time":38.83468911},
{"learn":[0.1834555158],"iteration":485,"passed_time":36.63881972,"remaining_time":38.74969823},
{"learn":[0.1834355802],"iteration":486,"passed_time":36.7057481,"remaining_time":38.66539789},
{"learn":[0.1834176751],"iteration":487,"passed_time":36.76691119,"remaining_time":38.57511994},
{"learn":[0.183399911],"iteration":488,"passed_time":36.83935547,"remaining_time":38.49674979},
{"learn":[0.1833782271],"iteration":489,"passed_time":36.93746958,"remaining_time":38.4451214},
{"learn":[0.1833630107],"iteration":490,"passed_time":37.03690194,"remaining_time":38.39467024},
{"learn":[0.1833491497],"iteration":491,"passed_time":37.13123039,"remaining_time":38.33875008},
{"learn":[0.183335475],"iteration":492,"passed_time":37.20219073,"remaining_time":38.2586424},
{"learn":[0.1833135703],"iteration":493,"passed_time":37.27775126,"remaining_time":38.18328368},
{"learn":[0.1832902308],"iteration":494,"passed_time":37.34236581,"remaining_time":38.09675704},
{"learn":[0.1832735384],"iteration":495,"passed_time":37.41161727,"remaining_time":38.01503045},
{"learn":[0.1832586951],"iteration":496,"passed_time":37.4760646,"remaining_time":37.92849194},
{"learn":[0.1832393835],"iteration":497,"passed_time":37.54060416,"remaining_time":37.84213512},
{"learn":[0.1832227364],"iteration":498,"passed_time":37.61372343,"remaining_time":37.76447983},
{"learn":[0.1832063629],"iteration":499,"passed_time":37.68158833,"remaining_time":37.68158833},
{"learn":[0.1831829636],"iteration":500,"passed_time":37.76734497,"remaining_time":37.61657713},
{"learn":[0.183167478],"iteration":501,"passed_time":37.86118887,"remaining_time":37.55950609},
{"learn":[0.1831481932],"iteration":502,"passed_time":37.96268321,"remaining_time":37.50984802},
{"learn":[0.1831286921],"iteration":503,"passed_time":38.06137677,"remaining_time":37.45722793},
{"learn":[0.1831105727],"iteration":504,"passed_time":38.14191448,"remaining_time":37.38662904},
{"learn":[0.1830958564],"iteration":505,"passed_time":38.20619337,"remaining_time":37.30011764},
{"learn":[0.1830823143],"iteration":506,"passed_time":38.27814531,"remaining_time":37.2211551},
{"learn":[0.1830646066],"iteration":507,"passed_time":38.34512958,"remaining_time":37.13740896},
{"learn":[0.1830143321],"iteration":508,"passed_time":38.41521015,"remaining_time":37.05671548},
{"learn":[0.1829980769],"iteration":509,"passed_time":38.48377947,"remaining_time":36.97461165},
{"learn":[0.1829745432],"iteration":510,"passed_time":38.54606758,"remaining_time":36.88655},
{"learn":[0.1829569323],"iteration":511,"passed_time":38.61004445,"remaining_time":36.80019861},
{"learn":[0.1829429879],"iteration":512,"passed_time":38.6727514,"remaining_time":36.71272892},
{"learn":[0.1829217671],"iteration":513,"passed_time":38.75145198,"remaining_time":36.64047794},
{"learn":[0.1828518251],"iteration":514,"passed_time":38.81241569,"remaining_time":36.55149827},
{"learn":[0.1828354142],"iteration":515,"passed_time":38.88178929,"remaining_time":36.47051554},
{"learn":[0.1828134108],"iteration":516,"passed_time":38.95020271,"remaining_time":36.38868067},
{"learn":[0.1827886205],"iteration":517,"passed_time":39.01505064,"remaining_time":36.30357994},
{"learn":[0.1827629227],"iteration":518,"passed_time":39.08332435,"remaining_time":36.2217322},
{"learn":[0.1827446595],"iteration":519,"passed_time":39.15384041,"remaining_time":36.14200653},
{"learn":[0.1827255893],"iteration":520,"passed_time":39.23009234,"remaining_time":36.0675897},
{"learn":[0.1827025011],"iteration":521,"passed_time":39.29927094,"remaining_time":35.98668871},
{"learn":[0.1826818934],"iteration":522,"passed_time":39.38032522,"remaining_time":35.91666373},
{"learn":[0.1826659696],"iteration":523,"passed_time":39.46835629,"remaining_time":35.85293434},
{"learn":[0.182644836],"iteration":524,"passed_time":39.55471805,"remaining_time":35.78760205},
{"learn":[0.1826291527],"iteration":525,"passed_time":39.66611557,"remaining_time":35.74475053},
{"learn":[0.1826142947],"iteration":526,"passed_time":39.77231127,"remaining_time":35.69697008},
{"learn":[0.1825910948],"iteration":527,"passed_time":39.85962889,"remaining_time":35.6320925},
{"learn":[0.1825769743],"iteration":528,"passed_time":39.93536966,"remaining_time":35.55682251},
{"learn":[0.1825618086],"iteration":529,"passed_time":40.01252616,"remaining_time":35.48280622},
{"learn":[0.1825461591],"iteration":530,"passed_time":40.08585497,"remaining_time":35.40539733},
{"learn":[0.1825300294],"iteration":531,"passed_time":40.16209082,"remaining_time":35.33056109},
{"learn":[0.1824882683],"iteration":532,"passed_time":40.25738642,"remaining_time":35.27241924},
{"learn":[0.1824621358],"iteration":533,"passed_time":40.33813723,"remaining_time":35.2014456},
{"learn":[0.1824478724],"iteration":534,"passed_time":40.4161253,"remaining_time":35.12803414},
{"learn":[0.1824258917],"iteration":535,"passed_time":40.48352186,"remaining_time":35.04543683},
{"learn":[0.1824087503],"iteration":536,"passed_time":40.54919519,"remaining_time":34.96141038},
{"learn":[0.1823898509],"iteration":537,"passed_time":40.61293958,"remaining_time":34.8757957},
{"learn":[0.1823774168],"iteration":538,"passed_time":40.67519953,"remaining_time":34.78899255},
{"learn":[0.1823589839],"iteration":539,"passed_time":40.73995422,"remaining_time":34.70440545},
{"learn":[0.1823447967],"iteration":540,"passed_time":40.80256042,"remaining_time":34.61806882},
{"learn":[0.1823299766],"iteration":541,"passed_time":40.8659605,"remaining_time":34.53249061},
{"learn":[0.1823096111],"iteration":542,"passed_time":40.92652952,"remaining_time":34.4446114},
{"learn":[0.1822811885],"iteration":543,"passed_time":40.99457597,"remaining_time":34.36310044},
{"learn":[0.1822642612],"iteration":544,"passed_time":41.09615743,"remaining_time":34.30963602},
{"learn":[0.1822467607],"iteration":545,"passed_time":41.17149876,"remaining_time":34.23417662},
{"learn":[0.1822312011],"iteration":546,"passed_time":41.24569117,"remaining_time":34.15776618},
{"learn":[0.1822131887],"iteration":547,"passed_time":41.31615986,"remaining_time":34.07829244},
{"learn":[0.1821954341],"iteration":548,"passed_time":41.38403233,"remaining_time":33.99671873},
{"learn":[0.1821436756],"iteration":549,"passed_time":41.46004834,"remaining_time":33.92185774},
{"learn":[0.1821244032],"iteration":550,"passed_time":41.52922067,"remaining_time":33.84141575},
{"learn":[0.1821005958],"iteration":551,"passed_time":41.59521021,"remaining_time":33.75843148},
{"learn":[0.1820857143],"iteration":552,"passed_time":41.65929383,"remaining_time":33.67396807},
{"learn":[0.1820691627],"iteration":553,"passed_time":41.72666639,"remaining_time":33.59222601},
{"learn":[0.1820516098],"iteration":554,"passed_time":41.79859145,"remaining_time":33.51418593},
{"learn":[0.1820286891],"iteration":555,"passed_time":41.8626519,"remaining_time":33.42988749},
{"learn":[0.1820130552],"iteration":556,"passed_time":41.92760535,"remaining_time":33.34637194},
{"learn":[0.1819974623],"iteration":557,"passed_time":41.99674654,"remaining_time":33.26624009},
{"learn":[0.1819815601],"iteration":558,"passed_time":42.06427183,"remaining_time":33.18487277},
{"learn":[0.1819683971],"iteration":559,"passed_time":42.12777377,"remaining_time":33.10039368},
{"learn":[0.1819555806],"iteration":560,"passed_time":42.18965224,"remaining_time":33.01471895},
{"learn":[0.1819426284],"iteration":561,"passed_time":42.25758445,"remaining_time":32.93384696},
{"learn":[0.1819254502],"iteration":562,"passed_time":42.32767998,"remaining_time":32.85470009},
{"learn":[0.1819066324],"iteration":563,"passed_time":42.39382232,"remaining_time":32.77252931},
{"learn":[0.1818935489],"iteration":564,"passed_time":42.46506582,"remaining_time":32.69434271},
{"learn":[0.1818749502],"iteration":565,"passed_time":42.5272564,"remaining_time":32.609239},
{"learn":[0.1818611399],"iteration":566,"passed_time":42.59227188,"remaining_time":32.52637341},
{"learn":[0.1818438819],"iteration":567,"passed_time":42.65779793,"remaining_time":32.44395899},
{"learn":[0.1818211678],"iteration":568,"passed_time":42.72278237,"remaining_time":32.36119368},
{"learn":[0.1818033171],"iteration":569,"passed_time":42.79434599,"remaining_time":32.28345399},
{"learn":[0.1817862612],"iteration":570,"passed_time":42.88749321,"remaining_time":32.22195199},
{"learn":[0.1817437074],"iteration":571,"passed_time":42.98950929,"remaining_time":32.16697548},
{"learn":[0.1817251573],"iteration":572,"passed_time":43.098992,"remaining_time":32.11739893},
{"learn":[0.1817094324],"iteration":573,"passed_time":43.20242259,"remaining_time":32.06312199},
{"learn":[0.1816890949],"iteration":574,"passed_time":43.28533215,"remaining_time":31.99350637},
{"learn":[0.181677147],"iteration":575,"passed_time":43.35537419,"remaining_time":31.91437267},
{"learn":[0.181653895],"iteration":576,"passed_time":43.42357544,"remaining_time":31.83392099},
{"learn":[0.1816317416],"iteration":577,"passed_time":43.49015834,"remaining_time":31.75233014},
{"learn":[0.1816106077],"iteration":578,"passed_time":43.56199477,"remaining_time":31.67461105},
{"learn":[0.1815834689],"iteration":579,"passed_time":43.63383539,"remaining_time":31.59691528},
{"learn":[0.1815707786],"iteration":580,"passed_time":43.70154619,"remaining_time":31.51626137},
{"learn":[0.1815517363],"iteration":581,"passed_time":43.766733,"remaining_time":31.43383917},
{"learn":[0.1815404332],"iteration":582,"passed_time":43.82865107,"remaining_time":31.34913807},
{"learn":[0.1815236159],"iteration":583,"passed_time":43.88668681,"remaining_time":31.26174951},
{"learn":[0.1815063264],"iteration":584,"passed_time":43.95093767,"remaining_time":31.17887031},
{"learn":[0.1814811284],"iteration":585,"passed_time":44.0193947,"remaining_time":31.09902629},
{"learn":[0.1814648846],"iteration":586,"passed_time":44.08555575,"remaining_time":31.01760566},
{"learn":[0.1814515982],"iteration":587,"passed_time":44.14843448,"remaining_time":30.93393708},
{"learn":[0.1814339256],"iteration":588,"passed_time":44.22449352,"remaining_time":30.85953622},
{"learn":[0.1814156978],"iteration":589,"passed_time":44.2950265,"remaining_time":30.7812896},
{"learn":[0.1814035907],"iteration":590,"passed_time":44.36364786,"remaining_time":30.70174615},
{"learn":[0.1813888067],"iteration":591,"passed_time":44.43205653,"remaining_time":30.62209301},
{"learn":[0.1813682761],"iteration":592,"passed_time":44.49852638,"remaining_time":30.54114711},
{"learn":[0.1813512199],"iteration":593,"passed_time":44.5662152,"remaining_time":30.46108312},
{"learn":[0.1813294],"iteration":594,"passed_time":44.64669717,"remaining_time":30.38976866},
{"learn":[0.1813113631],"iteration":595,"passed_time":44.74739281,"remaining_time":30.33212533},
{"learn":[0.1812970318],"iteration":596,"passed_time":44.84075055,"remaining_time":30.26938437},
{"learn":[0.1812800517],"iteration":597,"passed_time":44.91328358,"remaining_time":30.1925418},
{"learn":[0.1812628595],"iteration":598,"passed_time":44.98026908,"remaining_time":30.11199984},
{"learn":[0.181243979],"iteration":599,"passed_time":45.04300963,"remaining_time":30.02867308},
{"learn":[0.1812260183],"iteration":600,"passed_time":45.10930899,"remaining_time":29.94777751},
{"learn":[0.1811980625],"iteration":601,"passed_time":45.17508899,"remaining_time":29.86658707},
{"learn":[0.181182472],"iteration":602,"passed_time":45.24261946,"remaining_time":29.78660021},
{"learn":[0.1811628561],"iteration":603,"passed_time":45.30825153,"remaining_time":29.70540994},
{"learn":[0.1811507146],"iteration":604,"passed_time":45.37188449,"remaining_time":29.62296591},
{"learn":[0.1811384796],"iteration":605,"passed_time":45.44266534,"remaining_time":29.54523126},
{"learn":[0.1811189271],"iteration":606,"passed_time":45.50733696,"remaining_time":29.46356413},
{"learn":[0.1811027505],"iteration":607,"passed_time":45.57507766,"remaining_time":29.38393165},
{"learn":[0.1810840001],"iteration":608,"passed_time":45.64612977,"remaining_time":29.30646427},
{"learn":[0.1810684762],"iteration":609,"passed_time":45.73509639,"remaining_time":29.24047146},
{"learn":[0.1810535707],"iteration":610,"passed_time":45.83486875,"remaining_time":29.18128305},
{"learn":[0.1810335758],"iteration":611,"passed_time":45.92932122,"remaining_time":29.11858927},
{"learn":[0.1810141263],"iteration":612,"passed_time":46.00585514,"remaining_time":29.04447951},
{"learn":[0.1809931189],"iteration":613,"passed_time":46.07207992,"remaining_time":28.96388086},
{"learn":[0.1809791375],"iteration":614,"passed_time":46.13876686,"remaining_time":28.88361828},
{"learn":[0.1809628567],"iteration":615,"passed_time":46.20835383,"remaining_time":28.80520758},
{"learn":[0.1809435226],"iteration":616,"passed_time":46.27770658,"remaining_time":28.7266801},
{"learn":[0.180932133],"iteration":617,"passed_time":46.34442746,"remaining_time":28.64655548},
{"learn":[0.1809161443],"iteration":618,"passed_time":46.41174829,"remaining_time":28.56684345},
{"learn":[0.1808947905],"iteration":619,"passed_time":46.47742001,"remaining_time":28.48616065},
{"learn":[0.1808761997],"iteration":620,"passed_time":46.55501499,"remaining_time":28.41280303},
{"learn":[0.180860115],"iteration":621,"passed_time":46.62067943,"remaining_time":28.33218139},
{"learn":[0.1808482431],"iteration":622,"passed_time":46.6860565,"remaining_time":28.25143387},
{"learn":[0.1808244321],"iteration":623,"passed_time":46.75583456,"remaining_time":28.17338749},
{"learn":[0.1808005675],"iteration":624,"passed_time":46.82183952,"remaining_time":28.09310371},
{"learn":[0.1807807416],"iteration":625,"passed_time":46.89742426,"remaining_time":28.01858893},
{"learn":[0.1807663605],"iteration":626,"passed_time":46.99632494,"remaining_time":27.95794131},
{"learn":[0.1807550694],"iteration":627,"passed_time":47.08717238,"remaining_time":27.89240147},
{"learn":[0.1807352449],"iteration":628,"passed_time":47.16880443,"remaining_time":27.82134569},
{"learn":[0.1807136556],"iteration":629,"passed_time":47.23721145,"remaining_time":27.74248926},
{"learn":[0.1806964004],"iteration":630,"passed_time":47.30806612,"remaining_time":27.6650973},
{"learn":[0.1806874992],"iteration":631,"passed_time":47.39489065,"remaining_time":27.59702494},
{"learn":[0.1806767298],"iteration":632,"passed_time":47.46999392,"remaining_time":27.52209758},
{"learn":[0.1806583946],"iteration":633,"passed_time":47.53858833,"remaining_time":27.44341219},
{"learn":[0.1806207042],"iteration":634,"passed_time":47.61026285,"remaining_time":27.36652904},
{"learn":[0.1806092393],"iteration":635,"passed_time":47.67333187,"remaining_time":27.28473711},
{"learn":[0.1805919021],"iteration":636,"passed_time":47.73723721,"remaining_time":27.20348054},
{"learn":[0.1805778673],"iteration":637,"passed_time":47.80038881,"remaining_time":27.12185071},
{"learn":[0.1805656379],"iteration":638,"passed_time":47.8653642,"remaining_time":27.04130904},
{"learn":[0.1805467892],"iteration":639,"passed_time":47.92971002,"remaining_time":26.96046189},
{"learn":[0.1805313236],"iteration":640,"passed_time":47.99574248,"remaining_time":26.88061084},
{"learn":[0.1805097671],"iteration":641,"passed_time":48.06326166,"remaining_time":26.80163189},
{"learn":[0.1804904507],"iteration":642,"passed_time":48.14499759,"remaining_time":26.73058186},
{"learn":[0.1804751555],"iteration":643,"passed_time":48.2227843,"remaining_time":26.65731554},
{"learn":[0.1804550325],"iteration":644,"passed_time":48.29833466,"remaining_time":26.58280435},
{"learn":[0.1804416273],"iteration":645,"passed_time":48.37073152,"remaining_time":26.50656186},
{"learn":[0.1804211894],"iteration":646,"passed_time":48.44304121,"remaining_time":26.43028369},
{"learn":[0.1804050522],"iteration":647,"passed_time":48.51261942,"remaining_time":26.35253401},
{"learn":[0.1803866615],"iteration":648,"passed_time":48.58340884,"remaining_time":26.27546457},
{"learn":[0.1803561065],"iteration":649,"passed_time":48.66145478,"remaining_time":26.2023218},
{"learn":[0.1803373764],"iteration":650,"passed_time":48.73274113,"remaining_time":26.12554018},
{"learn":[0.1803229685],"iteration":651,"passed_time":48.7982554,"remaining_time":26.0456946},
{"learn":[0.1803065695],"iteration":652,"passed_time":48.8650766,"remaining_time":25.96658741},
{"learn":[0.1802887218],"iteration":653,"passed_time":48.9500192,"remaining_time":25.89710496},
{"learn":[0.1802700384],"iteration":654,"passed_time":49.02522567,"remaining_time":25.82244711},
{"learn":[0.180244807],"iteration":655,"passed_time":49.09073442,"remaining_time":25.7427022},
{"learn":[0.1802266061],"iteration":656,"passed_time":49.15705053,"remaining_time":25.66342212},
{"learn":[0.1801906652],"iteration":657,"passed_time":49.22765706,"remaining_time":25.58641142},
{"learn":[0.1801695657],"iteration":658,"passed_time":49.29468425,"remaining_time":25.50756803},
{"learn":[0.1801552398],"iteration":659,"passed_time":49.36947938,"remaining_time":25.4327621},
{"learn":[0.1801386494],"iteration":660,"passed_time":49.44100116,"remaining_time":25.35627745},
{"learn":[0.1801103923],"iteration":661,"passed_time":49.50902929,"remaining_time":25.27802402},
{"learn":[0.1800976377],"iteration":662,"passed_time":49.57717566,"remaining_time":25.19986154},
{"learn":[0.1800834544],"iteration":663,"passed_time":49.64289977,"remaining_time":25.1205035},
{"learn":[0.1800641893],"iteration":664,"passed_time":49.70920771,"remaining_time":25.04148058},
{"learn":[0.1800493772],"iteration":665,"passed_time":49.77776274,"remaining_time":24.96362276},
{"learn":[0.1800215973],"iteration":666,"passed_time":49.84579827,"remaining_time":24.88553347},
{"learn":[0.1800052871],"iteration":667,"passed_time":49.91076328,"remaining_time":24.80594822},
{"learn":[0.1799934908],"iteration":668,"passed_time":49.97643841,"remaining_time":24.72675802},
{"learn":[0.1799782563],"iteration":669,"passed_time":50.04487098,"remaining_time":24.64896631},
{"learn":[0.1799632582],"iteration":670,"passed_time":50.11108555,"remaining_time":24.57011497},
{"learn":[0.1799507228],"iteration":671,"passed_time":50.17132862,"remaining_time":24.48838659},
{"learn":[0.1799325748],"iteration":672,"passed_time":50.23993144,"remaining_time":24.41078392},
{"learn":[0.1799123172],"iteration":673,"passed_time":50.31375007,"remaining_time":24.33573074},
{"learn":[0.1798937763],"iteration":674,"passed_time":50.40340833,"remaining_time":24.26830771},
{"learn":[0.1798793691],"iteration":675,"passed_time":50.48873246,"remaining_time":24.19874159},
{"learn":[0.1798669493],"iteration":676,"passed_time":50.58910175,"remaining_time":24.13630704},
{"learn":[0.1798519817],"iteration":677,"passed_time":50.68211765,"remaining_time":24.07026826},
{"learn":[0.1798357491],"iteration":678,"passed_time":50.77532113,"remaining_time":24.00423871},
{"learn":[0.1798255311],"iteration":679,"passed_time":50.86657655,"remaining_time":23.93721249},
{"learn":[0.1798101582],"iteration":680,"passed_time":50.95350206,"remaining_time":23.86808687},
{"learn":[0.1797951827],"iteration":681,"passed_time":51.04654416,"remaining_time":23.80176106},
{"learn":[0.179781332],"iteration":682,"passed_time":51.12376725,"remaining_time":23.72801496},
{"learn":[0.1797675228],"iteration":683,"passed_time":51.22735173,"remaining_time":23.66643735},
{"learn":[0.1797513649],"iteration":684,"passed_time":51.31157177,"remaining_time":23.59583227},
{"learn":[0.1797338671],"iteration":685,"passed_time":51.38771431,"remaining_time":23.52149022},
{"learn":[0.1797191689],"iteration":686,"passed_time":51.47923746,"remaining_time":23.4541504},
{"learn":[0.1797012561],"iteration":687,"passed_time":51.56263163,"remaining_time":23.38305388},
{"learn":[0.1796877912],"iteration":688,"passed_time":51.64823953,"remaining_time":23.31292089},
{"learn":[0.1796687456],"iteration":689,"passed_time":51.72402551,"remaining_time":23.2383303},
{"learn":[0.17964899],"iteration":690,"passed_time":51.78798744,"remaining_time":23.1584488},
{"learn":[0.1796295619],"iteration":691,"passed_time":51.85335285,"remaining_time":23.07923798},
{"learn":[0.1796159999],"iteration":692,"passed_time":51.91760063,"remaining_time":22.999572},
{"learn":[0.1795986313],"iteration":693,"passed_time":51.98501874,"remaining_time":22.92134832},
{"learn":[0.1795805555],"iteration":694,"passed_time":52.0627952,"remaining_time":22.84770149},
{"learn":[0.1795652725],"iteration":695,"passed_time":52.13404752,"remaining_time":22.77119317},
{"learn":[0.1795514669],"iteration":696,"passed_time":52.20652715,"remaining_time":22.69523346},
{"learn":[0.1795368237],"iteration":697,"passed_time":52.27994671,"remaining_time":22.61969041},
{"learn":[0.1795205884],"iteration":698,"passed_time":52.36031478,"remaining_time":22.54714556},
{"learn":[0.1795060981],"iteration":699,"passed_time":52.46777418,"remaining_time":22.48618894},
{"learn":[0.1794866753],"iteration":700,"passed_time":52.54610509,"remaining_time":22.41267535},
{"learn":[0.1794647219],"iteration":701,"passed_time":52.610722,"remaining_time":22.33332643},
{"learn":[0.1794460725],"iteration":702,"passed_time":52.67427485,"remaining_time":22.25356989},
{"learn":[0.1794328602],"iteration":703,"passed_time":52.74089014,"remaining_time":22.17514699},
{"learn":[0.1794095709],"iteration":704,"passed_time":52.80904747,"remaining_time":22.09740284},
{"learn":[0.1793958493],"iteration":705,"passed_time":52.88564791,"remaining_time":22.02320182},
{"learn":[0.179381356],"iteration":706,"passed_time":52.96188946,"remaining_time":21.94884528},
{"learn":[0.1793673704],"iteration":707,"passed_time":53.03250723,"remaining_time":21.872164},
{"learn":[0.1793501879],"iteration":708,"passed_time":53.10131383,"remaining_time":21.79475645},
{"learn":[0.1793321767],"iteration":709,"passed_time":53.1693188,"remaining_time":21.71704571},
{"learn":[0.1793164244],"iteration":710,"passed_time":53.24264538,"remaining_time":21.64152534},
{"learn":[0.1792979236],"iteration":711,"passed_time":53.31994297,"remaining_time":21.56761738},
{"learn":[0.1792774743],"iteration":712,"passed_time":53.42182732,"remaining_time":21.50359669},
{"learn":[0.1792631655],"iteration":713,"passed_time":53.52786059,"remaining_time":21.44113183},
{"learn":[0.1792453484],"iteration":714,"passed_time":53.62663377,"remaining_time":21.37565122},
{"learn":[0.1792301918],"iteration":715,"passed_time":53.72243227,"remaining_time":21.30889772},
{"learn":[0.1792077565],"iteration":716,"passed_time":53.81220159,"remaining_time":21.23968347},
{"learn":[0.1791887721],"iteration":717,"passed_time":53.91098492,"remaining_time":21.17395229},
{"learn":[0.1791619779],"iteration":718,"passed_time":54.00975424,"remaining_time":21.1081237},
{"learn":[0.1791445593],"iteration":719,"passed_time":54.1098302,"remaining_time":21.04271174},
{"learn":[0.1791258895],"iteration":720,"passed_time":54.19987954,"remaining_time":20.97332371},
{"learn":[0.1791081976],"iteration":721,"passed_time":54.27326013,"remaining_time":20.89746027},
{"learn":[0.1790908076],"iteration":722,"passed_time":54.34325538,"remaining_time":20.82030669},
{"learn":[0.1790742],"iteration":723,"passed_time":54.42254034,"remaining_time":20.74671427},
{"learn":[0.1790525167],"iteration":724,"passed_time":54.50624863,"remaining_time":20.67478396},
{"learn":[0.1790322126],"iteration":725,"passed_time":54.59103428,"remaining_time":20.60322781},
{"learn":[0.1790164549],"iteration":726,"passed_time":54.68953014,"remaining_time":20.53678367},
{"learn":[0.1790009127],"iteration":727,"passed_time":54.77480541,"remaining_time":20.46531191},
{"learn":[0.1789874731],"iteration":728,"passed_time":54.85301869,"remaining_time":20.39117704},
{"learn":[0.178965443],"iteration":729,"passed_time":54.99673045,"remaining_time":20.34125647},
{"learn":[0.1789451966],"iteration":730,"passed_time":55.11629221,"remaining_time":20.28219235},
{"learn":[0.1789318971],"iteration":731,"passed_time":55.24469133,"remaining_time":20.22619847},
{"learn":[0.1789137807],"iteration":732,"passed_time":55.45611621,"remaining_time":20.2002497},
{"learn":[0.1789023303],"iteration":733,"passed_time":55.54910044,"remaining_time":20.13087291},
{"learn":[0.1788878996],"iteration":734,"passed_time":55.66239869,"remaining_time":20.06875599},
{"learn":[0.178874642],"iteration":735,"passed_time":55.76571373,"remaining_time":20.00291905},
{"learn":[0.1788565957],"iteration":736,"passed_time":55.85518586,"remaining_time":19.93204054},
{"learn":[0.1788475713],"iteration":737,"passed_time":55.95458468,"remaining_time":19.86463575},
{"learn":[0.1788247091],"iteration":738,"passed_time":56.05116726,"remaining_time":19.79614974},
{"learn":[0.1788082461],"iteration":739,"passed_time":56.16375199,"remaining_time":19.73321016},
{"learn":[0.178792856],"iteration":740,"passed_time":56.27205271,"remaining_time":19.66863921},
{"learn":[0.178776045],"iteration":741,"passed_time":56.37685089,"remaining_time":19.60273252},
{"learn":[0.1787620975],"iteration":742,"passed_time":56.49341685,"remaining_time":19.54079156},
{"learn":[0.1787435901],"iteration":743,"passed_time":56.6028137,"remaining_time":19.47623697},
{"learn":[0.1787209646],"iteration":744,"passed_time":56.70065254,"remaining_time":19.4076059},
{"learn":[0.178701765],"iteration":745,"passed_time":56.79360905,"remaining_time":19.33723418},
{"learn":[0.1786841948],"iteration":746,"passed_time":56.89526017,"remaining_time":19.26974675},
{"learn":[0.1786666248],"iteration":747,"passed_time":56.99406892,"remaining_time":19.20121039},
{"learn":[0.1786508005],"iteration":748,"passed_time":57.08940678,"remaining_time":19.13143004},
{"learn":[0.1786399792],"iteration":749,"passed_time":57.18015851,"remaining_time":19.06005284},
{"learn":[0.1786220048],"iteration":750,"passed_time":57.27532882,"remaining_time":18.99008905},
{"learn":[0.1786039762],"iteration":751,"passed_time":57.36257751,"remaining_time":18.91744578},
{"learn":[0.1785855701],"iteration":752,"passed_time":57.45894779,"remaining_time":18.84775578},
{"learn":[0.1785691629],"iteration":753,"passed_time":57.57553174,"remaining_time":18.78458993},
{"learn":[0.1785547795],"iteration":754,"passed_time":57.68192189,"remaining_time":18.71797465},
{"learn":[0.1785403191],"iteration":755,"passed_time":57.78366031,"remaining_time":18.6497528},
{"learn":[0.1785277807],"iteration":756,"passed_time":57.94394789,"remaining_time":18.6002369},
{"learn":[0.1785138609],"iteration":757,"passed_time":58.1741187,"remaining_time":18.57273974},
{"learn":[0.1784963526],"iteration":758,"passed_time":58.34592645,"remaining_time":18.52617691},
{"learn":[0.1784833856],"iteration":759,"passed_time":58.46100932,"remaining_time":18.46137136},
{"learn":[0.1784621864],"iteration":760,"passed_time":58.60311768,"remaining_time":18.40492132},
{"learn":[0.1784460527],"iteration":761,"passed_time":58.72282713,"remaining_time":18.34125047},
{"learn":[0.1784297342],"iteration":762,"passed_time":58.83767798,"remaining_time":18.27592357},
{"learn":[0.1784151547],"iteration":763,"passed_time":58.97485436,"remaining_time":18.21736339},
{"learn":[0.1784054272],"iteration":764,"passed_time":59.10703311,"remaining_time":18.15706246},
{"learn":[0.1783891882],"iteration":765,"passed_time":59.24708685,"remaining_time":18.09897954},
{"learn":[0.1783724528],"iteration":766,"passed_time":59.32332811,"remaining_time":18.02129785},
{"learn":[0.1783504785],"iteration":767,"passed_time":59.40866395,"remaining_time":17.94636724},
{"learn":[0.1783350627],"iteration":768,"passed_time":59.48876534,"remaining_time":17.86983718},
{"learn":[0.1783211994],"iteration":769,"passed_time":59.55846984,"remaining_time":17.79019229},
{"learn":[0.178306083],"iteration":770,"passed_time":59.6319734,"remaining_time":17.71170157},
{"learn":[0.178282808],"iteration":771,"passed_time":59.70695849,"remaining_time":17.63366132},
{"learn":[0.1782596063],"iteration":772,"passed_time":59.8020233,"remaining_time":17.5615256},
{"learn":[0.1782442216],"iteration":773,"passed_time":59.88209699,"remaining_time":17.48495338},
{"learn":[0.1782284399],"iteration":774,"passed_time":59.96402854,"remaining_time":17.40891151},
{"learn":[0.1782140835],"iteration":775,"passed_time":60.03299324,"remaining_time":17.32911145},
{"learn":[0.1782032322],"iteration":776,"passed_time":60.10031348,"remaining_time":17.24886732},
{"learn":[0.1781905619],"iteration":777,"passed_time":60.16815951,"remaining_time":17.16880644},
{"learn":[0.178172071],"iteration":778,"passed_time":60.23789993,"remaining_time":17.08931436},
{"learn":[0.1781525408],"iteration":779,"passed_time":60.31517623,"remaining_time":17.01197278},
{"learn":[0.1781386448],"iteration":780,"passed_time":60.38127506,"remaining_time":16.93149711},
{"learn":[0.1781247419],"iteration":781,"passed_time":60.44838509,"remaining_time":16.85134009},
{"learn":[0.1781115049],"iteration":782,"passed_time":60.53048128,"remaining_time":16.77536965},
{"learn":[0.1780940066],"iteration":783,"passed_time":60.61415651,"remaining_time":16.69981863},
{"learn":[0.1780757921],"iteration":784,"passed_time":60.81301432,"remaining_time":16.65579373},
{"learn":[0.178059368],"iteration":785,"passed_time":60.88084723,"remaining_time":16.57570141},
{"learn":[0.1779913236],"iteration":786,"passed_time":60.96526339,"remaining_time":16.50012847},
{"learn":[0.1779488231],"iteration":787,"passed_time":61.04867061,"remaining_time":16.42426164},
{"learn":[0.1779304671],"iteration":788,"passed_time":61.15637383,"remaining_time":16.3548731},
{"learn":[0.1779146069],"iteration":789,"passed_time":61.27080925,"remaining_time":16.28717714},
{"learn":[0.177905116],"iteration":790,"passed_time":61.36116034,"remaining_time":16.21299938},
{"learn":[0.1778844043],"iteration":791,"passed_time":61.44523103,"remaining_time":16.13713138},
{"learn":[0.177867002],"iteration":792,"passed_time":61.52157429,"remaining_time":16.05922557},
{"learn":[0.1778556504],"iteration":793,"passed_time":61.59743665,"remaining_time":15.98119893},
{"learn":[0.1778401076],"iteration":794,"passed_time":61.6816259,"remaining_time":15.90532492},
{"learn":[0.1778247676],"iteration":795,"passed_time":61.76217224,"remaining_time":15.8284964},
{"learn":[0.1778090546],"iteration":796,"passed_time":61.83364598,"remaining_time":15.74934772},
{"learn":[0.1777967274],"iteration":797,"passed_time":61.91874302,"remaining_time":15.67366678},
{"learn":[0.1777832509],"iteration":798,"passed_time":62.01744483,"remaining_time":15.60138474},
{"learn":[0.1777673154],"iteration":799,"passed_time":62.09465517,"remaining_time":15.52366379},
{"learn":[0.1777530249],"iteration":800,"passed_time":62.18256845,"remaining_time":15.44860315},
{"learn":[0.1777403655],"iteration":801,"passed_time":62.26438426,"remaining_time":15.37200509},
{"learn":[0.1777248354],"iteration":802,"passed_time":62.35056132,"remaining_time":15.29646398},
{"learn":[0.1777077768],"iteration":803,"passed_time":62.42730466,"remaining_time":15.21859666},
{"learn":[0.1776888076],"iteration":804,"passed_time":62.52038612,"remaining_time":15.1446898},
{"learn":[0.1776740598],"iteration":805,"passed_time":62.59975838,"remaining_time":15.06743564},
{"learn":[0.177659258],"iteration":806,"passed_time":62.68143331,"remaining_time":14.99072692},
{"learn":[0.1776442302],"iteration":807,"passed_time":62.75680626,"remaining_time":14.91250842},
{"learn":[0.1776283657],"iteration":808,"passed_time":62.84929473,"remaining_time":14.83833782},
{"learn":[0.1776150863],"iteration":809,"passed_time":62.97421609,"remaining_time":14.7717297},
{"learn":[0.1775524298],"iteration":810,"passed_time":63.20564463,"remaining_time":14.72979881},
{"learn":[0.1775417383],"iteration":811,"passed_time":63.32169657,"remaining_time":14.66068837},
{"learn":[0.1775262562],"iteration":812,"passed_time":63.41834205,"remaining_time":14.58699872},
{"learn":[0.1775079107],"iteration":813,"passed_time":63.51978526,"remaining_time":14.51434897},
{"learn":[0.1774953782],"iteration":814,"passed_time":63.58832322,"remaining_time":14.43415926},
{"learn":[0.1774817615],"iteration":815,"passed_time":63.64990232,"remaining_time":14.35242895},
{"learn":[0.1774679396],"iteration":816,"passed_time":63.73137645,"remaining_time":14.27520427},
{"learn":[0.1774545211],"iteration":817,"passed_time":63.79808923,"remaining_time":14.19468489},
{"learn":[0.1773998512],"iteration":818,"passed_time":63.86049585,"remaining_time":14.11324756},
{"learn":[0.1773879501],"iteration":819,"passed_time":63.91769446,"remaining_time":14.03071342},
{"learn":[0.1773597455],"iteration":820,"passed_time":63.98292902,"remaining_time":13.94999305},
{"learn":[0.1773223629],"iteration":821,"passed_time":64.06355185,"remaining_time":13.87264261},
{"learn":[0.1773053618],"iteration":822,"passed_time":64.13320292,"remaining_time":13.79292456},
{"learn":[0.1772935675],"iteration":823,"passed_time":64.20064191,"remaining_time":13.71275847},
{"learn":[0.1772687051],"iteration":824,"passed_time":64.26574976,"remaining_time":13.63212874},
{"learn":[0.1772557151],"iteration":825,"passed_time":64.35246535,"remaining_time":13.55608834},
{"learn":[0.1772360397],"iteration":826,"passed_time":64.41690085,"remaining_time":13.47536136},
{"learn":[0.1772208984],"iteration":827,"passed_time":64.48224845,"remaining_time":13.3948632},
{"learn":[0.1772067095],"iteration":828,"passed_time":64.54897395,"remaining_time":13.31468582},
{"learn":[0.1771831614],"iteration":829,"passed_time":64.61246546,"remaining_time":13.23387847},
{"learn":[0.177166867],"iteration":830,"passed_time":64.68676439,"remaining_time":13.15531069},
{"learn":[0.1771534409],"iteration":831,"passed_time":64.77519009,"remaining_time":13.07960569},
{"learn":[0.1771311769],"iteration":832,"passed_time":64.84871473,"remaining_time":13.00088278},
{"learn":[0.1771115709],"iteration":833,"passed_time":64.92381908,"remaining_time":12.92248677},
{"learn":[0.1770920209],"iteration":834,"passed_time":64.9930333,"remaining_time":12.84293472},
{"learn":[0.1770786007],"iteration":835,"passed_time":65.06129149,"remaining_time":12.76321986},
{"learn":[0.1770672075],"iteration":836,"passed_time":65.12854674,"remaining_time":12.68333706},
{"learn":[0.1770539217],"iteration":837,"passed_time":65.2046386,"remaining_time":12.60519266},
{"learn":[0.1770434373],"iteration":838,"passed_time":65.28704532,"remaining_time":12.52826495},
{"learn":[0.1770308731],"iteration":839,"passed_time":65.36733963,"remaining_time":12.45092183},
{"learn":[0.1770132959],"iteration":840,"passed_time":65.44466136,"remaining_time":12.3730097},
{"learn":[0.1769773177],"iteration":841,"passed_time":65.51415747,"remaining_time":12.2936305},
{"learn":[0.1769630021],"iteration":842,"passed_time":65.58059512,"remaining_time":12.21370514},
{"learn":[0.1769287742],"iteration":843,"passed_time":65.65865141,"remaining_time":12.13595927},
{"learn":[0.1769161832],"iteration":844,"passed_time":65.75580452,"remaining_time":12.06171562},
{"learn":[0.1768965905],"iteration":845,"passed_time":65.83309347,"remaining_time":11.98380188},
{"learn":[0.1768779282],"iteration":846,"passed_time":65.90418777,"remaining_time":11.90477064},
{"learn":[0.1768614832],"iteration":847,"passed_time":65.97834753,"remaining_time":11.82630758},
{"learn":[0.1768466161],"iteration":848,"passed_time":66.05122355,"remaining_time":11.74762633},
{"learn":[0.1767990829],"iteration":849,"passed_time":66.12838509,"remaining_time":11.66971502},
{"learn":[0.1767798444],"iteration":850,"passed_time":66.23151048,"remaining_time":11.59635142},
{"learn":[0.1767629791],"iteration":851,"passed_time":66.30203179,"remaining_time":11.51725435},
{"learn":[0.1767507901],"iteration":852,"passed_time":66.37103411,"remaining_time":11.43791561},
{"learn":[0.1767385742],"iteration":853,"passed_time":66.44115161,"remaining_time":11.35879173},
{"learn":[0.1767275129],"iteration":854,"passed_time":66.50697994,"remaining_time":11.27896151},
{"learn":[0.1767098678],"iteration":855,"passed_time":66.57669854,"remaining_time":11.19981845},
{"learn":[0.1766918643],"iteration":856,"passed_time":66.65164805,"remaining_time":11.12157021},
{"learn":[0.1766753663],"iteration":857,"passed_time":66.72375465,"remaining_time":11.04285916},
{"learn":[0.1766640284],"iteration":858,"passed_time":66.79611821,"remaining_time":10.96420567},
{"learn":[0.1766557182],"iteration":859,"passed_time":66.86480359,"remaining_time":10.88496803},
{"learn":[0.1766413473],"iteration":860,"passed_time":66.94611492,"remaining_time":10.80779323},
{"learn":[0.1766233707],"iteration":861,"passed_time":67.03827331,"remaining_time":10.73234538},
{"learn":[0.1766038697],"iteration":862,"passed_time":67.13498369,"remaining_time":10.65758142},
{"learn":[0.1765051779],"iteration":863,"passed_time":67.21813064,"remaining_time":10.58063167},
{"learn":[0.1764652625],"iteration":864,"passed_time":67.30358699,"remaining_time":10.50402803},
{"learn":[0.1764474538],"iteration":865,"passed_time":67.39434398,"remaining_time":10.42822413},
{"learn":[0.1764241605],"iteration":866,"passed_time":67.47062333,"remaining_time":10.35016483},
{"learn":[0.1764044687],"iteration":867,"passed_time":67.54348656,"remaining_time":10.27159012},
{"learn":[0.1763873646],"iteration":868,"passed_time":67.62002467,"remaining_time":10.19358255},
{"learn":[0.1763682585],"iteration":869,"passed_time":67.70716705,"remaining_time":10.11716289},
{"learn":[0.1763548238],"iteration":870,"passed_time":67.78588522,"remaining_time":10.03947095},
{"learn":[0.1763385472],"iteration":871,"passed_time":67.85712719,"remaining_time":9.96067922},
{"learn":[0.1763191429],"iteration":872,"passed_time":67.92309362,"remaining_time":9.881137331},
{"learn":[0.1763058511],"iteration":873,"passed_time":67.99634677,"remaining_time":9.802676994},
{"learn":[0.1762921021],"iteration":874,"passed_time":68.07614797,"remaining_time":9.725163996},
{"learn":[0.1762737335],"iteration":875,"passed_time":68.15071928,"remaining_time":9.646905468},
{"learn":[0.1762590933],"iteration":876,"passed_time":68.26370228,"remaining_time":9.574042623},
{"learn":[0.1762391086],"iteration":877,"passed_time":68.33836136,"remaining_time":9.495763196},
{"learn":[0.1762291008],"iteration":878,"passed_time":68.43777201,"remaining_time":9.420899218},
{"learn":[0.1762148045],"iteration":879,"passed_time":68.53369911,"remaining_time":9.345504424},
{"learn":[0.1761982597],"iteration":880,"passed_time":68.60583855,"remaining_time":9.266849929},
{"learn":[0.1761768138],"iteration":881,"passed_time":68.68139651,"remaining_time":9.18866756},
{"learn":[0.1761528812],"iteration":882,"passed_time":68.7542457,"remaining_time":9.110132216},
{"learn":[0.1761371692],"iteration":883,"passed_time":68.84629981,"remaining_time":9.034129839},
{"learn":[0.1761157143],"iteration":884,"passed_time":68.92097271,"remaining_time":8.955832612},
{"learn":[0.176104708],"iteration":885,"passed_time":68.98815194,"remaining_time":8.876579369},
{"learn":[0.1760967429],"iteration":886,"passed_time":69.06065087,"remaining_time":8.798031058},
{"learn":[0.1760815275],"iteration":887,"passed_time":69.13740545,"remaining_time":8.72003312},
{"learn":[0.1760711492],"iteration":888,"passed_time":69.20330999,"remaining_time":8.64068325},
{"learn":[0.1760565034],"iteration":889,"passed_time":69.27510817,"remaining_time":8.562092021},
{"learn":[0.1760419565],"iteration":890,"passed_time":69.34484005,"remaining_time":8.48326326},
{"learn":[0.1760291573],"iteration":891,"passed_time":69.42293164,"remaining_time":8.40546706},
{"learn":[0.1760117888],"iteration":892,"passed_time":69.53770338,"remaining_time":8.332065243},
{"learn":[0.1760011434],"iteration":893,"passed_time":69.62247112,"remaining_time":8.255013354},
{"learn":[0.1759836681],"iteration":894,"passed_time":69.7024212,"remaining_time":8.177379023},
{"learn":[0.175972411],"iteration":895,"passed_time":69.78492849,"remaining_time":8.100036342},
{"learn":[0.1759575991],"iteration":896,"passed_time":69.86764759,"remaining_time":8.022706468},
{"learn":[0.1759412571],"iteration":897,"passed_time":69.96812907,"remaining_time":7.947382143},
{"learn":[0.1759256364],"iteration":898,"passed_time":70.06915159,"remaining_time":7.872062637},
{"learn":[0.1759086637],"iteration":899,"passed_time":70.17777035,"remaining_time":7.797530039},
{"learn":[0.1758808505],"iteration":900,"passed_time":70.26191532,"remaining_time":7.720232649},
{"learn":[0.1758651731],"iteration":901,"passed_time":70.33196841,"remaining_time":7.641389029},
{"learn":[0.1758479933],"iteration":902,"passed_time":70.40945552,"remaining_time":7.563363439},
{"learn":[0.1758346107],"iteration":903,"passed_time":70.4959795,"remaining_time":7.486298708},
{"learn":[0.1758204639],"iteration":904,"passed_time":70.57261374,"remaining_time":7.408174923},
{"learn":[0.1758092109],"iteration":905,"passed_time":70.65548691,"remaining_time":7.330701732},
{"learn":[0.1757956006],"iteration":906,"passed_time":70.7233333,"remaining_time":7.251675851},
{"learn":[0.1757780818],"iteration":907,"passed_time":70.81079197,"remaining_time":7.174661742},
{"learn":[0.1757639608],"iteration":908,"passed_time":70.91197493,"remaining_time":7.098998591},
{"learn":[0.175750837],"iteration":909,"passed_time":71.07104694,"remaining_time":7.029004643},
{"learn":[0.1757364867],"iteration":910,"passed_time":71.17106189,"remaining_time":6.953045564},
{"learn":[0.1757228819],"iteration":911,"passed_time":71.26650769,"remaining_time":6.876592847},
{"learn":[0.1757046824],"iteration":912,"passed_time":71.35292865,"remaining_time":6.799238546},
{"learn":[0.1756898463],"iteration":913,"passed_time":71.42852252,"remaining_time":6.720845664},
{"learn":[0.1756748223],"iteration":914,"passed_time":71.50253738,"remaining_time":6.642312215},
{"learn":[0.1756598036],"iteration":915,"passed_time":71.56695193,"remaining_time":6.562908256},
{"learn":[0.1756452228],"iteration":916,"passed_time":71.64085947,"remaining_time":6.484396222},
{"learn":[0.175631723],"iteration":917,"passed_time":71.71141225,"remaining_time":6.405594558},
{"learn":[0.1756204943],"iteration":918,"passed_time":71.77913339,"remaining_time":6.326561267},
{"learn":[0.1756032321],"iteration":919,"passed_time":71.84549894,"remaining_time":6.247434691},
{"learn":[0.1755890152],"iteration":920,"passed_time":71.92345723,"remaining_time":6.169330208},
{"learn":[0.1755721527],"iteration":921,"passed_time":71.99060426,"remaining_time":6.090311423},
{"learn":[0.1755618931],"iteration":922,"passed_time":72.04886373,"remaining_time":6.010576931},
{"learn":[0.1755482446],"iteration":923,"passed_time":72.11717973,"remaining_time":5.931716082},
{"learn":[0.175532736],"iteration":924,"passed_time":72.21486263,"remaining_time":5.855259132},
{"learn":[0.1755181562],"iteration":925,"passed_time":72.28400672,"remaining_time":5.776475699},
{"learn":[0.1754982266],"iteration":926,"passed_time":72.36011829,"remaining_time":5.698261742},
{"learn":[0.1754823868],"iteration":927,"passed_time":72.4554283,"remaining_time":5.621541851},
{"learn":[0.175465404],"iteration":928,"passed_time":72.53135741,"remaining_time":5.543300728},
{"learn":[0.1754537988],"iteration":929,"passed_time":72.61281112,"remaining_time":5.465480407},
{"learn":[0.1754397823],"iteration":930,"passed_time":72.687285,"remaining_time":5.387134979},
{"learn":[0.1754287834],"iteration":931,"passed_time":72.75829084,"remaining_time":5.308544825},
{"learn":[0.1754126344],"iteration":932,"passed_time":72.8284171,"remaining_time":5.229907766},
{"learn":[0.1753641643],"iteration":933,"passed_time":72.90162113,"remaining_time":5.151506418},
{"learn":[0.1753463977],"iteration":934,"passed_time":72.97049725,"remaining_time":5.072815317},
{"learn":[0.1753313174],"iteration":935,"passed_time":73.03588888,"remaining_time":4.993906932},
{"learn":[0.1753107605],"iteration":936,"passed_time":73.10203784,"remaining_time":4.915078318},
{"learn":[0.1752969837],"iteration":937,"passed_time":73.19325484,"remaining_time":4.837933689},
{"learn":[0.1752805289],"iteration":938,"passed_time":73.26157998,"remaining_time":4.759271969},
{"learn":[0.1752647164],"iteration":939,"passed_time":73.33539281,"remaining_time":4.68098252},
{"learn":[0.1752573487],"iteration":940,"passed_time":73.40153642,"remaining_time":4.602221731},
{"learn":[0.1752422563],"iteration":941,"passed_time":73.48252658,"remaining_time":4.524401849},
{"learn":[0.1752295329],"iteration":942,"passed_time":73.56455751,"remaining_time":4.446638153},
{"learn":[0.175206625],"iteration":943,"passed_time":73.70818265,"remaining_time":4.37251931},
{"learn":[0.17519992],"iteration":944,"passed_time":73.81618225,"remaining_time":4.296179919},
{"learn":[0.1751808957],"iteration":945,"passed_time":73.89012588,"remaining_time":4.217829596},
{"learn":[0.1751667979],"iteration":946,"passed_time":73.96630243,"remaining_time":4.139613547},
{"learn":[0.1751523708],"iteration":947,"passed_time":74.03434574,"remaining_time":4.060955674},
{"learn":[0.1751365303],"iteration":948,"passed_time":74.12436457,"remaining_time":3.983501152},
{"learn":[0.1751221034],"iteration":949,"passed_time":74.21541785,"remaining_time":3.906074624},
{"learn":[0.1751032251],"iteration":950,"passed_time":74.3197158,"remaining_time":3.829301865},
{"learn":[0.1750826092],"iteration":951,"passed_time":74.40676069,"remaining_time":3.751601379},
{"learn":[0.1750625623],"iteration":952,"passed_time":74.47948652,"remaining_time":3.673175096},
{"learn":[0.1750489114],"iteration":953,"passed_time":74.55755116,"remaining_time":3.59501819},
{"learn":[0.175040083],"iteration":954,"passed_time":74.65500083,"remaining_time":3.517774908},
{"learn":[0.1750239081],"iteration":955,"passed_time":74.74713804,"remaining_time":3.440244847},
{"learn":[0.1750011815],"iteration":956,"passed_time":74.8196774,"remaining_time":3.361803687},
{"learn":[0.1749819485],"iteration":957,"passed_time":74.89982119,"remaining_time":3.283708236},
{"learn":[0.1749663904],"iteration":958,"passed_time":74.96839159,"remaining_time":3.205113718},
{"learn":[0.1749490871],"iteration":959,"passed_time":75.03868877,"remaining_time":3.126612032},
{"learn":[0.174940529],"iteration":960,"passed_time":75.11322702,"remaining_time":3.048299536},
{"learn":[0.1749259641],"iteration":961,"passed_time":75.19605232,"remaining_time":2.970322233},
{"learn":[0.1749117904],"iteration":962,"passed_time":75.31430382,"remaining_time":2.893695993},
{"learn":[0.174900094],"iteration":963,"passed_time":75.43453304,"remaining_time":2.817057251},
{"learn":[0.1748840458],"iteration":964,"passed_time":75.5430668,"remaining_time":2.739903977},
{"learn":[0.1748696155],"iteration":965,"passed_time":75.6650164,"remaining_time":2.663157927},
{"learn":[0.1748530996],"iteration":966,"passed_time":75.78410946,"remaining_time":2.586220902},
{"learn":[0.1748350106],"iteration":967,"passed_time":75.9061482,"remaining_time":2.509294155},
{"learn":[0.1748192402],"iteration":968,"passed_time":76.03312008,"remaining_time":2.432432118},
{"learn":[0.1748063516],"iteration":969,"passed_time":76.14841258,"remaining_time":2.355105544},
{"learn":[0.1747953032],"iteration":970,"passed_time":76.23159276,"remaining_time":2.276741699},
{"learn":[0.1747805546],"iteration":971,"passed_time":76.31371709,"remaining_time":2.198337529},
{"learn":[0.1747684038],"iteration":972,"passed_time":76.38400442,"remaining_time":2.119597245},
{"learn":[0.1747014776],"iteration":973,"passed_time":76.4875231,"remaining_time":2.041761397},
{"learn":[0.1746849183],"iteration":974,"passed_time":76.57109479,"remaining_time":1.963361405},
{"learn":[0.1746675794],"iteration":975,"passed_time":76.65549932,"remaining_time":1.884971295},
{"learn":[0.1746487983],"iteration":976,"passed_time":76.73200977,"remaining_time":1.806383034},
{"learn":[0.1746362786],"iteration":977,"passed_time":76.81248634,"remaining_time":1.727888241},
{"learn":[0.1746217122],"iteration":978,"passed_time":76.8915369,"remaining_time":1.64935881},
{"learn":[0.1746081347],"iteration":979,"passed_time":76.96888575,"remaining_time":1.570793587},
{"learn":[0.1745902477],"iteration":980,"passed_time":77.05239934,"remaining_time":1.492350242},
{"learn":[0.1745771821],"iteration":981,"passed_time":77.15040756,"remaining_time":1.414162257},
{"learn":[0.1745634723],"iteration":982,"passed_time":77.22230303,"remaining_time":1.335482351},
{"learn":[0.1745468526],"iteration":983,"passed_time":77.28947597,"remaining_time":1.256739447},
{"learn":[0.1745306287],"iteration":984,"passed_time":77.3599866,"remaining_time":1.178070862},
{"learn":[0.1745194379],"iteration":985,"passed_time":77.42458548,"remaining_time":1.099334885},
{"learn":[0.1745056829],"iteration":986,"passed_time":77.49384607,"remaining_time":1.020688955},
{"learn":[0.1744925499],"iteration":987,"passed_time":77.56086185,"remaining_time":0.9420347593},
{"learn":[0.1744767703],"iteration":988,"passed_time":77.63650472,"remaining_time":0.8635000525},
{"learn":[0.1744646007],"iteration":989,"passed_time":77.7539931,"remaining_time":0.7853938697},
{"learn":[0.1744500258],"iteration":990,"passed_time":77.82361926,"remaining_time":0.7067735352},
{"learn":[0.1744394733],"iteration":991,"passed_time":77.89027035,"remaining_time":0.6281473415},
{"learn":[0.1744231767],"iteration":992,"passed_time":77.98229218,"remaining_time":0.5497241141},
{"learn":[0.1744105858],"iteration":993,"passed_time":78.05724244,"remaining_time":0.4711704775},
{"learn":[0.1743905664],"iteration":994,"passed_time":78.15362199,"remaining_time":0.3927317688},
{"learn":[0.1743647517],"iteration":995,"passed_time":78.24948024,"remaining_time":0.3142549407},
{"learn":[0.1743528518],"iteration":996,"passed_time":78.35432389,"remaining_time":0.2357702825},
{"learn":[0.1743378741],"iteration":997,"passed_time":78.46345167,"remaining_time":0.1572413861},
{"learn":[0.1743208882],"iteration":998,"passed_time":78.54909185,"remaining_time":0.07862771957},
{"learn":[0.1743017817],"iteration":999,"passed_time":78.66582348,"remaining_time":0}
]}